{
"meta":{"test_sets":[],"test_metrics":[],"learn_metrics":[{"best_value":"Min","name":"Logloss"}],"launch_mode":"Train","parameters":"","iteration_count":1000,"learn_sets":["learn"],"name":"experiment"},
"iterations":[
{"learn":[0.6897485957],"iteration":0,"passed_time":0.02756784364,"remaining_time":27.54027579},
{"learn":[0.686794281],"iteration":1,"passed_time":0.0554449323,"remaining_time":27.66702122},
{"learn":[0.6839610268],"iteration":2,"passed_time":0.08076903838,"remaining_time":26.84224376},
{"learn":[0.6809435452],"iteration":3,"passed_time":0.1028603141,"remaining_time":25.6122182},
{"learn":[0.6781673431],"iteration":4,"passed_time":0.1304917698,"remaining_time":25.96786219},
{"learn":[0.6755109675],"iteration":5,"passed_time":0.1590973959,"remaining_time":26.35713525},
{"learn":[0.6724427167],"iteration":6,"passed_time":0.1837335344,"remaining_time":26.06391424},
{"learn":[0.668982618],"iteration":7,"passed_time":0.2092494611,"remaining_time":25.94693318},
{"learn":[0.6655640322],"iteration":8,"passed_time":0.2333652659,"remaining_time":25.69610872},
{"learn":[0.6628755682],"iteration":9,"passed_time":0.259645295,"remaining_time":25.70488421},
{"learn":[0.6596180411],"iteration":10,"passed_time":0.2873234171,"remaining_time":25.83298723},
{"learn":[0.6560382843],"iteration":11,"passed_time":0.3099447671,"remaining_time":25.51878582},
{"learn":[0.6524877548],"iteration":12,"passed_time":0.3327092006,"remaining_time":25.26030623},
{"learn":[0.6494303311],"iteration":13,"passed_time":0.361779645,"remaining_time":25.47962357},
{"learn":[0.6457392749],"iteration":14,"passed_time":0.3859293811,"remaining_time":25.34269603},
{"learn":[0.6426361308],"iteration":15,"passed_time":0.4093640117,"remaining_time":25.17588672},
{"learn":[0.6400373122],"iteration":16,"passed_time":0.4308400144,"remaining_time":24.91269024},
{"learn":[0.6369451074],"iteration":17,"passed_time":0.4540391271,"remaining_time":24.77035682},
{"learn":[0.6335068871],"iteration":18,"passed_time":0.4764677138,"remaining_time":24.60078038},
{"learn":[0.6305318159],"iteration":19,"passed_time":0.5026891112,"remaining_time":24.63176645},
{"learn":[0.6272164513],"iteration":20,"passed_time":0.5256359379,"remaining_time":24.50464682},
{"learn":[0.6244330687],"iteration":21,"passed_time":0.5515236572,"remaining_time":24.51773349},
{"learn":[0.621429219],"iteration":22,"passed_time":0.586779035,"remaining_time":24.92535292},
{"learn":[0.6191277223],"iteration":23,"passed_time":0.6237292125,"remaining_time":25.36498797},
{"learn":[0.6164178848],"iteration":24,"passed_time":0.6537731648,"remaining_time":25.49715343},
{"learn":[0.6136618222],"iteration":25,"passed_time":0.6818019531,"remaining_time":25.54135009},
{"learn":[0.6111329584],"iteration":26,"passed_time":0.7134576846,"remaining_time":25.710901},
{"learn":[0.6082362007],"iteration":27,"passed_time":0.7582319328,"remaining_time":26.32147995},
{"learn":[0.6056370455],"iteration":28,"passed_time":0.8114834115,"remaining_time":27.17070319},
{"learn":[0.6030125898],"iteration":29,"passed_time":0.8386070449,"remaining_time":27.11496112},
{"learn":[0.6003983442],"iteration":30,"passed_time":0.8772039759,"remaining_time":27.41969847},
{"learn":[0.597381704],"iteration":31,"passed_time":0.9067984554,"remaining_time":27.43065327},
{"learn":[0.5942906772],"iteration":32,"passed_time":0.9349088079,"remaining_time":27.39566113},
{"learn":[0.5919862074],"iteration":33,"passed_time":0.9621291517,"remaining_time":27.33578708},
{"learn":[0.5892399059],"iteration":34,"passed_time":0.9945313151,"remaining_time":27.42064912},
{"learn":[0.586947946],"iteration":35,"passed_time":1.019397487,"remaining_time":27.29719938},
{"learn":[0.5848067789],"iteration":36,"passed_time":1.047139385,"remaining_time":27.25392508},
{"learn":[0.5824211906],"iteration":37,"passed_time":1.073181617,"remaining_time":27.16843987},
{"learn":[0.5797097823],"iteration":38,"passed_time":1.097069048,"remaining_time":27.03290654},
{"learn":[0.5773043913],"iteration":39,"passed_time":1.125664324,"remaining_time":27.01594376},
{"learn":[0.5747621761],"iteration":40,"passed_time":1.15232027,"remaining_time":26.95305216},
{"learn":[0.5723379921],"iteration":41,"passed_time":1.17813649,"remaining_time":26.87273232},
{"learn":[0.5697490468],"iteration":42,"passed_time":1.21075256,"remaining_time":26.94628373},
{"learn":[0.5673157187],"iteration":43,"passed_time":1.234442819,"remaining_time":26.82107579},
{"learn":[0.5655087303],"iteration":44,"passed_time":1.261775768,"remaining_time":26.77768575},
{"learn":[0.5624688092],"iteration":45,"passed_time":1.289510624,"remaining_time":26.74332903},
{"learn":[0.5594275418],"iteration":46,"passed_time":1.315329443,"remaining_time":26.67040339},
{"learn":[0.5566806793],"iteration":47,"passed_time":1.345161781,"remaining_time":26.67904198},
{"learn":[0.5542528489],"iteration":48,"passed_time":1.370901099,"remaining_time":26.60667235},
{"learn":[0.5520583882],"iteration":49,"passed_time":1.400424974,"remaining_time":26.6080745},
{"learn":[0.5505111358],"iteration":50,"passed_time":1.429673053,"remaining_time":26.6031319},
{"learn":[0.5474996006],"iteration":51,"passed_time":1.4559435,"remaining_time":26.54296997},
{"learn":[0.5454855526],"iteration":52,"passed_time":1.480194669,"remaining_time":26.44800664},
{"learn":[0.5432609109],"iteration":53,"passed_time":1.507314724,"remaining_time":26.40592091},
{"learn":[0.5410294813],"iteration":54,"passed_time":1.533318813,"remaining_time":26.34520505},
{"learn":[0.5389555202],"iteration":55,"passed_time":1.562778422,"remaining_time":26.34397911},
{"learn":[0.5364673839],"iteration":56,"passed_time":1.587849947,"remaining_time":26.26916667},
{"learn":[0.5349196266],"iteration":57,"passed_time":1.612527786,"remaining_time":26.18967542},
{"learn":[0.5316767973],"iteration":58,"passed_time":1.649495409,"remaining_time":26.3080539},
{"learn":[0.5294001523],"iteration":59,"passed_time":1.67280041,"remaining_time":26.20720642},
{"learn":[0.5275341483],"iteration":60,"passed_time":1.702185365,"remaining_time":26.20249276},
{"learn":[0.5254229377],"iteration":61,"passed_time":1.732789199,"remaining_time":26.21542369},
{"learn":[0.5234463636],"iteration":62,"passed_time":1.763601865,"remaining_time":26.23007854},
{"learn":[0.5212892645],"iteration":63,"passed_time":1.790411731,"remaining_time":26.18477157},
{"learn":[0.5191830467],"iteration":64,"passed_time":1.815501243,"remaining_time":26.1152871},
{"learn":[0.5178127289],"iteration":65,"passed_time":1.844526297,"remaining_time":26.10284184},
{"learn":[0.5157538021],"iteration":66,"passed_time":1.868180857,"remaining_time":26.01511552},
{"learn":[0.5138153749],"iteration":67,"passed_time":1.899285685,"remaining_time":26.03138616},
{"learn":[0.5115862454],"iteration":68,"passed_time":1.93104607,"remaining_time":26.05512885},
{"learn":[0.5092305576],"iteration":69,"passed_time":1.955845548,"remaining_time":25.98480514},
{"learn":[0.5068973092],"iteration":70,"passed_time":1.980747205,"remaining_time":25.91710075},
{"learn":[0.5053690742],"iteration":71,"passed_time":2.006496216,"remaining_time":25.86150678},
{"learn":[0.5036111719],"iteration":72,"passed_time":2.035081128,"remaining_time":25.84274255},
{"learn":[0.5011826123],"iteration":73,"passed_time":2.062958316,"remaining_time":25.81485677},
{"learn":[0.4992907468],"iteration":74,"passed_time":2.088949136,"remaining_time":25.76370601},
{"learn":[0.4975060856],"iteration":75,"passed_time":2.113285871,"remaining_time":25.69310716},
{"learn":[0.4956558452],"iteration":76,"passed_time":2.143847313,"remaining_time":25.69832558},
{"learn":[0.4934314279],"iteration":77,"passed_time":2.174591106,"remaining_time":25.70478205},
{"learn":[0.4912753947],"iteration":78,"passed_time":2.199455198,"remaining_time":25.64174984},
{"learn":[0.4894753624],"iteration":79,"passed_time":2.227176012,"remaining_time":25.61252413},
{"learn":[0.4874903735],"iteration":80,"passed_time":2.255928046,"remaining_time":25.59503548},
{"learn":[0.4859748167],"iteration":81,"passed_time":2.280785524,"remaining_time":25.53367208},
{"learn":[0.4843184527],"iteration":82,"passed_time":2.309459104,"remaining_time":25.51534937},
{"learn":[0.4830227459],"iteration":83,"passed_time":2.334694934,"remaining_time":25.45929237},
{"learn":[0.481729227],"iteration":84,"passed_time":2.361573834,"remaining_time":25.42164775},
{"learn":[0.479635463],"iteration":85,"passed_time":2.387677469,"remaining_time":25.37601403},
{"learn":[0.4779194103],"iteration":86,"passed_time":2.411660524,"remaining_time":25.30857539},
{"learn":[0.4760474598],"iteration":87,"passed_time":2.437296336,"remaining_time":25.25925294},
{"learn":[0.4748965993],"iteration":88,"passed_time":2.470678125,"remaining_time":25.28975024},
{"learn":[0.4733373418],"iteration":89,"passed_time":2.493972111,"remaining_time":25.21682913},
{"learn":[0.4713539797],"iteration":90,"passed_time":2.52373911,"remaining_time":25.2096577},
{"learn":[0.4694271649],"iteration":91,"passed_time":2.551147857,"remaining_time":25.17872015},
{"learn":[0.4678205322],"iteration":92,"passed_time":2.576187829,"remaining_time":25.12475657},
{"learn":[0.4662078128],"iteration":93,"passed_time":2.601860273,"remaining_time":25.07750434},
{"learn":[0.4644240772],"iteration":94,"passed_time":2.625974158,"remaining_time":25.01585909},
{"learn":[0.4624563666],"iteration":95,"passed_time":2.652282964,"remaining_time":24.97566458},
{"learn":[0.4612703043],"iteration":96,"passed_time":2.678490878,"remaining_time":24.93481715},
{"learn":[0.4593402077],"iteration":97,"passed_time":2.704344014,"remaining_time":24.89100307},
{"learn":[0.4577298445],"iteration":98,"passed_time":2.730932078,"remaining_time":24.85424043},
{"learn":[0.455869282],"iteration":99,"passed_time":2.763193195,"remaining_time":24.86873876},
{"learn":[0.4541614476],"iteration":100,"passed_time":2.798694267,"remaining_time":24.91114996},
{"learn":[0.4525362183],"iteration":101,"passed_time":2.824081512,"remaining_time":24.86299213},
{"learn":[0.4501826062],"iteration":102,"passed_time":2.84840008,"remaining_time":24.80596963},
{"learn":[0.4489606969],"iteration":103,"passed_time":2.876983953,"remaining_time":24.78632329},
{"learn":[0.4474437097],"iteration":104,"passed_time":2.902375472,"remaining_time":24.73929569},
{"learn":[0.4460252313],"iteration":105,"passed_time":2.927001458,"remaining_time":24.68621985},
{"learn":[0.4441768983],"iteration":106,"passed_time":2.949893872,"remaining_time":24.61920773},
{"learn":[0.4425380931],"iteration":107,"passed_time":2.973605281,"remaining_time":24.55977695},
{"learn":[0.4410774007],"iteration":108,"passed_time":2.998978319,"remaining_time":24.51458424},
{"learn":[0.4395654342],"iteration":109,"passed_time":3.024963302,"remaining_time":24.47470308},
{"learn":[0.4385139802],"iteration":110,"passed_time":3.047728982,"remaining_time":24.40928887},
{"learn":[0.4367040466],"iteration":111,"passed_time":3.091499657,"remaining_time":24.51117585},
{"learn":[0.4348740578],"iteration":112,"passed_time":3.164114875,"remaining_time":24.83690171},
{"learn":[0.4338159561],"iteration":113,"passed_time":3.232524046,"remaining_time":25.12295004},
{"learn":[0.4326791763],"iteration":114,"passed_time":3.282150186,"remaining_time":25.25828621},
{"learn":[0.4314458791],"iteration":115,"passed_time":3.324531079,"remaining_time":25.33521961},
{"learn":[0.4299419347],"iteration":116,"passed_time":3.354638475,"remaining_time":25.31748524},
{"learn":[0.4284288462],"iteration":117,"passed_time":3.381588902,"remaining_time":25.27594416},
{"learn":[0.4270009995],"iteration":118,"passed_time":3.410187687,"remaining_time":25.2468517},
{"learn":[0.4252234908],"iteration":119,"passed_time":3.434976021,"remaining_time":25.18982415},
{"learn":[0.4236574734],"iteration":120,"passed_time":3.459012287,"remaining_time":25.12786612},
{"learn":[0.4221492094],"iteration":121,"passed_time":3.483649816,"remaining_time":25.07085687},
{"learn":[0.4208746517],"iteration":122,"passed_time":3.508747505,"remaining_time":25.01765497},
{"learn":[0.4196428411],"iteration":123,"passed_time":3.535345779,"remaining_time":24.97550728},
{"learn":[0.4180505977],"iteration":124,"passed_time":3.560424009,"remaining_time":24.92296806},
{"learn":[0.4169471404],"iteration":125,"passed_time":3.586461587,"remaining_time":24.87751927},
{"learn":[0.4157786089],"iteration":126,"passed_time":3.610716591,"remaining_time":24.82012271},
{"learn":[0.4147773069],"iteration":127,"passed_time":3.638551095,"remaining_time":24.78762934},
{"learn":[0.4130071752],"iteration":128,"passed_time":3.662336333,"remaining_time":24.7278678},
{"learn":[0.411499332],"iteration":129,"passed_time":3.688980575,"remaining_time":24.68779308},
{"learn":[0.4104241483],"iteration":130,"passed_time":3.721274765,"remaining_time":24.68540283},
{"learn":[0.4089849135],"iteration":131,"passed_time":3.745905836,"remaining_time":24.63216868},
{"learn":[0.4072897294],"iteration":132,"passed_time":3.774043651,"remaining_time":24.6022244},
{"learn":[0.4055798474],"iteration":133,"passed_time":3.803489777,"remaining_time":24.58076229},
{"learn":[0.4045328813],"iteration":134,"passed_time":3.826940194,"remaining_time":24.52076495},
{"learn":[0.4027942209],"iteration":135,"passed_time":3.853512874,"remaining_time":24.48114061},
{"learn":[0.4016230527],"iteration":136,"passed_time":3.882820565,"remaining_time":24.45893539},
{"learn":[0.400372393],"iteration":137,"passed_time":3.906858328,"remaining_time":24.40370927},
{"learn":[0.3990479357],"iteration":138,"passed_time":3.935355216,"remaining_time":24.37655281},
{"learn":[0.3978240069],"iteration":139,"passed_time":3.958294317,"remaining_time":24.31523652},
{"learn":[0.3967465232],"iteration":140,"passed_time":3.982703848,"remaining_time":24.26342274},
{"learn":[0.3954576044],"iteration":141,"passed_time":4.005908599,"remaining_time":24.20471534},
{"learn":[0.3941443948],"iteration":142,"passed_time":4.031840673,"remaining_time":24.16284935},
{"learn":[0.3927566584],"iteration":143,"passed_time":4.055211357,"remaining_time":24.10597862},
{"learn":[0.3913286434],"iteration":144,"passed_time":4.080483327,"remaining_time":24.060781},
{"learn":[0.3899350447],"iteration":145,"passed_time":4.104283612,"remaining_time":24.00724798},
{"learn":[0.3885823979],"iteration":146,"passed_time":4.130952579,"remaining_time":23.97076564},
{"learn":[0.3873425091],"iteration":147,"passed_time":4.159911129,"remaining_time":23.9475965},
{"learn":[0.3863591867],"iteration":148,"passed_time":4.182906329,"remaining_time":23.89029051},
{"learn":[0.3852137397],"iteration":149,"passed_time":4.2115376,"remaining_time":23.86537974},
{"learn":[0.3842777925],"iteration":150,"passed_time":4.235439571,"remaining_time":23.81382911},
{"learn":[0.3834620083],"iteration":151,"passed_time":4.260986363,"remaining_time":23.77181866},
{"learn":[0.3819264524],"iteration":152,"passed_time":4.286542018,"remaining_time":23.73007248},
{"learn":[0.3806259492],"iteration":153,"passed_time":4.310415863,"remaining_time":23.67929753},
{"learn":[0.379101641],"iteration":154,"passed_time":4.333204111,"remaining_time":23.62295145},
{"learn":[0.3777735093],"iteration":155,"passed_time":4.359196897,"remaining_time":23.58437296},
{"learn":[0.3764030232],"iteration":156,"passed_time":4.382040833,"remaining_time":23.52904728},
{"learn":[0.374961292],"iteration":157,"passed_time":4.406525468,"remaining_time":23.48287623},
{"learn":[0.3739305384],"iteration":158,"passed_time":4.429596763,"remaining_time":23.42950238},
{"learn":[0.3726684907],"iteration":159,"passed_time":4.454159191,"remaining_time":23.38433575},
{"learn":[0.3718469003],"iteration":160,"passed_time":4.477527272,"remaining_time":23.33320113},
{"learn":[0.3709040249],"iteration":161,"passed_time":4.500207723,"remaining_time":23.2788523},
{"learn":[0.3694352543],"iteration":162,"passed_time":4.524251943,"remaining_time":23.23189495},
{"learn":[0.3681419597],"iteration":163,"passed_time":4.555713086,"remaining_time":23.22302524},
{"learn":[0.3666129393],"iteration":164,"passed_time":4.57761218,"remaining_time":23.16549194},
{"learn":[0.3652152454],"iteration":165,"passed_time":4.602288734,"remaining_time":23.12234219},
{"learn":[0.364356069],"iteration":166,"passed_time":4.624753278,"remaining_time":23.06838012},
{"learn":[0.3631373574],"iteration":167,"passed_time":4.648205908,"remaining_time":23.0196864},
{"learn":[0.3621618327],"iteration":168,"passed_time":4.673848105,"remaining_time":22.98205784},
{"learn":[0.3608884811],"iteration":169,"passed_time":4.701069681,"remaining_time":22.95228138},
{"learn":[0.3599159016],"iteration":170,"passed_time":4.725526148,"remaining_time":22.90912969},
{"learn":[0.3586530966],"iteration":171,"passed_time":4.749420399,"remaining_time":22.8634889},
{"learn":[0.3569905057],"iteration":172,"passed_time":4.773503276,"remaining_time":22.81900121},
{"learn":[0.3559889513],"iteration":173,"passed_time":4.798989893,"remaining_time":22.78141179},
{"learn":[0.3550357258],"iteration":174,"passed_time":4.826079091,"remaining_time":22.75151571},
{"learn":[0.3542046827],"iteration":175,"passed_time":4.850700827,"remaining_time":22.71009933},
{"learn":[0.3536436137],"iteration":176,"passed_time":4.875053014,"remaining_time":22.66761938},
{"learn":[0.3526404605],"iteration":177,"passed_time":4.898435148,"remaining_time":22.62086343},
{"learn":[0.3515830881],"iteration":178,"passed_time":4.921883239,"remaining_time":22.57467117},
{"learn":[0.3504448498],"iteration":179,"passed_time":4.945310956,"remaining_time":22.5286388},
{"learn":[0.3490584317],"iteration":180,"passed_time":4.967941086,"remaining_time":22.47924724},
{"learn":[0.3479246252],"iteration":181,"passed_time":4.997612764,"remaining_time":22.46179803},
{"learn":[0.3470294616],"iteration":182,"passed_time":5.020162356,"remaining_time":22.41241883},
{"learn":[0.3459192444],"iteration":183,"passed_time":5.044236684,"remaining_time":22.37009312},
{"learn":[0.3450061013],"iteration":184,"passed_time":5.06829528,"remaining_time":22.32789542},
{"learn":[0.3439478313],"iteration":185,"passed_time":5.094177552,"remaining_time":22.2938738},
{"learn":[0.3429079617],"iteration":186,"passed_time":5.117591291,"remaining_time":22.24920706},
{"learn":[0.3416613691],"iteration":187,"passed_time":5.142178985,"remaining_time":22.20983689},
{"learn":[0.3406113456],"iteration":188,"passed_time":5.164400618,"remaining_time":22.16047038},
{"learn":[0.3397751976],"iteration":189,"passed_time":5.188457989,"remaining_time":22.11921564},
{"learn":[0.3387466879],"iteration":190,"passed_time":5.215710669,"remaining_time":22.09167503},
{"learn":[0.337816603],"iteration":191,"passed_time":5.24018417,"remaining_time":22.05244172},
{"learn":[0.3369266005],"iteration":192,"passed_time":5.262682658,"remaining_time":22.00510314},
{"learn":[0.3359581723],"iteration":193,"passed_time":5.288700185,"remaining_time":21.97264097},
{"learn":[0.3350351839],"iteration":194,"passed_time":5.312527224,"remaining_time":21.93120213},
{"learn":[0.3340171926],"iteration":195,"passed_time":5.3348819,"remaining_time":21.8839033},
{"learn":[0.3328771311],"iteration":196,"passed_time":5.35861745,"remaining_time":21.84248636},
{"learn":[0.3317118252],"iteration":197,"passed_time":5.381421082,"remaining_time":21.79747327},
{"learn":[0.3307317846],"iteration":198,"passed_time":5.411747531,"remaining_time":21.78296368},
{"learn":[0.3293401494],"iteration":199,"passed_time":5.434814639,"remaining_time":21.73925856},
{"learn":[0.3287981258],"iteration":200,"passed_time":5.458134802,"remaining_time":21.69676471},
{"learn":[0.3276574752],"iteration":201,"passed_time":5.480200894,"remaining_time":21.6495065},
{"learn":[0.3268522936],"iteration":202,"passed_time":5.506807361,"remaining_time":21.6203225},
{"learn":[0.3260344898],"iteration":203,"passed_time":5.529761725,"remaining_time":21.5769134},
{"learn":[0.3253417857],"iteration":204,"passed_time":5.554472951,"remaining_time":21.54051706},
{"learn":[0.324432934],"iteration":205,"passed_time":5.576943405,"remaining_time":21.4955974},
{"learn":[0.3234211136],"iteration":206,"passed_time":5.600960129,"remaining_time":21.45681827},
{"learn":[0.3225251086],"iteration":207,"passed_time":5.624985146,"remaining_time":21.41821267},
{"learn":[0.3214722241],"iteration":208,"passed_time":5.647923742,"remaining_time":21.37563483},
{"learn":[0.3201893358],"iteration":209,"passed_time":5.670798131,"remaining_time":21.33300249},
{"learn":[0.31899901],"iteration":210,"passed_time":5.695107708,"remaining_time":21.29592408},
{"learn":[0.3182758443],"iteration":211,"passed_time":5.720703952,"remaining_time":21.26374865},
{"learn":[0.3173500229],"iteration":212,"passed_time":5.743112175,"remaining_time":21.21985578},
{"learn":[0.3162995226],"iteration":213,"passed_time":5.767816782,"remaining_time":21.18459809},
{"learn":[0.3154848323],"iteration":214,"passed_time":5.802028831,"remaining_time":21.18415178},
{"learn":[0.3147912025],"iteration":215,"passed_time":5.836308916,"remaining_time":21.18363977},
{"learn":[0.314130166],"iteration":216,"passed_time":5.862946351,"remaining_time":21.1552396},
{"learn":[0.3132249608],"iteration":217,"passed_time":5.890812672,"remaining_time":21.13126381},
{"learn":[0.3124588237],"iteration":218,"passed_time":5.916583707,"remaining_time":21.09978025},
{"learn":[0.3114480411],"iteration":219,"passed_time":5.947687292,"remaining_time":21.08725494},
{"learn":[0.310717751],"iteration":220,"passed_time":5.971457549,"remaining_time":21.04871236},
{"learn":[0.3102163988],"iteration":221,"passed_time":5.996906009,"remaining_time":21.01618412},
{"learn":[0.3093727336],"iteration":222,"passed_time":6.021711943,"remaining_time":20.98148063},
{"learn":[0.3087181204],"iteration":223,"passed_time":6.048063251,"remaining_time":20.95221912},
{"learn":[0.307923317],"iteration":224,"passed_time":6.07258503,"remaining_time":20.91668177},
{"learn":[0.3071211086],"iteration":225,"passed_time":6.097985716,"remaining_time":20.88425197},
{"learn":[0.306377467],"iteration":226,"passed_time":6.124537231,"remaining_time":20.85580299},
{"learn":[0.305275328],"iteration":227,"passed_time":6.150853814,"remaining_time":20.8265752},
{"learn":[0.3044171614],"iteration":228,"passed_time":6.179244746,"remaining_time":20.80435677},
{"learn":[0.3038566814],"iteration":229,"passed_time":6.205615977,"remaining_time":20.77532305},
{"learn":[0.3031075422],"iteration":230,"passed_time":6.234379867,"remaining_time":20.75427757},
{"learn":[0.3024891124],"iteration":231,"passed_time":6.275570799,"remaining_time":20.77430333},
{"learn":[0.3015391125],"iteration":232,"passed_time":6.307269536,"remaining_time":20.7625568},
{"learn":[0.3006654347],"iteration":233,"passed_time":6.338433926,"remaining_time":20.74889054},
{"learn":[0.3001980221],"iteration":234,"passed_time":6.36814615,"remaining_time":20.73034811},
{"learn":[0.2992644871],"iteration":235,"passed_time":6.398171021,"remaining_time":20.71272313},
{"learn":[0.2983994764],"iteration":236,"passed_time":6.430280862,"remaining_time":20.7017059},
{"learn":[0.2974960944],"iteration":237,"passed_time":6.457645048,"remaining_time":20.67531734},
{"learn":[0.2968033622],"iteration":238,"passed_time":6.484051701,"remaining_time":20.64587173},
{"learn":[0.2957898028],"iteration":239,"passed_time":6.509159188,"remaining_time":20.61233743},
{"learn":[0.2949722795],"iteration":240,"passed_time":6.533854075,"remaining_time":20.57757362},
{"learn":[0.294368828],"iteration":241,"passed_time":6.561880787,"remaining_time":20.55332908},
{"learn":[0.2936677652],"iteration":242,"passed_time":6.587916652,"remaining_time":20.52285146},
{"learn":[0.2924016223],"iteration":243,"passed_time":6.612338431,"remaining_time":20.48740924},
{"learn":[0.2916173374],"iteration":244,"passed_time":6.64156811,"remaining_time":20.46687315},
{"learn":[0.2910514719],"iteration":245,"passed_time":6.677801376,"remaining_time":20.46773267},
{"learn":[0.2904439814],"iteration":246,"passed_time":6.704379001,"remaining_time":20.43885582},
{"learn":[0.2894058789],"iteration":247,"passed_time":6.734958848,"remaining_time":20.42213328},
{"learn":[0.2886611153],"iteration":248,"passed_time":6.759475848,"remaining_time":20.3870135},
{"learn":[0.2877828093],"iteration":249,"passed_time":6.787020865,"remaining_time":20.36106259},
{"learn":[0.2870178784],"iteration":250,"passed_time":6.813984685,"remaining_time":20.33336466},
{"learn":[0.2858919256],"iteration":251,"passed_time":6.839046867,"remaining_time":20.300028},
{"learn":[0.2852616591],"iteration":252,"passed_time":6.866259231,"remaining_time":20.27310532},
{"learn":[0.2845858125],"iteration":253,"passed_time":6.895128991,"remaining_time":20.25104814},
{"learn":[0.2838071935],"iteration":254,"passed_time":6.92133482,"remaining_time":20.22115467},
{"learn":[0.2829212862],"iteration":255,"passed_time":6.947743272,"remaining_time":20.19187888},
{"learn":[0.2822647375],"iteration":256,"passed_time":6.985383734,"remaining_time":20.19509772},
{"learn":[0.2813595323],"iteration":257,"passed_time":7.015098363,"remaining_time":20.17520537},
{"learn":[0.2805151659],"iteration":258,"passed_time":7.046794736,"remaining_time":20.16090695},
{"learn":[0.2795420254],"iteration":259,"passed_time":7.075431881,"remaining_time":20.13776766},
{"learn":[0.2786661877],"iteration":260,"passed_time":7.115465064,"remaining_time":20.14685319},
{"learn":[0.2781105602],"iteration":261,"passed_time":7.146272461,"remaining_time":20.12957663},
{"learn":[0.2775081747],"iteration":262,"passed_time":7.170491066,"remaining_time":20.09373352},
{"learn":[0.2768694653],"iteration":263,"passed_time":7.196970939,"remaining_time":20.06428262},
{"learn":[0.2764265958],"iteration":264,"passed_time":7.221355693,"remaining_time":20.02904315},
{"learn":[0.2755291883],"iteration":265,"passed_time":7.250606016,"remaining_time":20.00731134},
{"learn":[0.2749443615],"iteration":266,"passed_time":7.275590629,"remaining_time":19.97381248},
{"learn":[0.2741753073],"iteration":267,"passed_time":7.303944934,"remaining_time":19.94958094},
{"learn":[0.2737011068],"iteration":268,"passed_time":7.329151627,"remaining_time":19.9167652},
{"learn":[0.2732215208],"iteration":269,"passed_time":7.3553929,"remaining_time":19.88680303},
{"learn":[0.2723192888],"iteration":270,"passed_time":7.387741006,"remaining_time":19.87329592},
{"learn":[0.2717358645],"iteration":271,"passed_time":7.463547385,"remaining_time":19.97596506},
{"learn":[0.2710102306],"iteration":272,"passed_time":7.549257828,"remaining_time":20.10370125},
{"learn":[0.2702369129],"iteration":273,"passed_time":7.621629865,"remaining_time":20.19453752},
{"learn":[0.2698363697],"iteration":274,"passed_time":7.673236062,"remaining_time":20.22944053},
{"learn":[0.2691661049],"iteration":275,"passed_time":7.722972049,"remaining_time":20.25881074},
{"learn":[0.2683855786],"iteration":276,"passed_time":7.778669113,"remaining_time":20.30316884},
{"learn":[0.2678809727],"iteration":277,"passed_time":7.833358533,"remaining_time":20.34419015},
{"learn":[0.267293874],"iteration":278,"passed_time":7.864920098,"remaining_time":20.32475767},
{"learn":[0.2668105013],"iteration":279,"passed_time":7.890225539,"remaining_time":20.28915139},
{"learn":[0.2660594828],"iteration":280,"passed_time":7.914077055,"remaining_time":20.24989823},
{"learn":[0.2654386408],"iteration":281,"passed_time":7.961809517,"remaining_time":20.27155756},
{"learn":[0.2647919094],"iteration":282,"passed_time":7.991998438,"remaining_time":20.24827873},
{"learn":[0.2642197889],"iteration":283,"passed_time":8.050188341,"remaining_time":20.29554525},
{"learn":[0.2636289316],"iteration":284,"passed_time":8.099650991,"remaining_time":20.32017705},
{"learn":[0.2629419215],"iteration":285,"passed_time":8.137742553,"remaining_time":20.31590274},
{"learn":[0.261984152],"iteration":286,"passed_time":8.165911479,"remaining_time":20.28674176},
{"learn":[0.2613993252],"iteration":287,"passed_time":8.201240716,"remaining_time":20.27528955},
{"learn":[0.2607915822],"iteration":288,"passed_time":8.228692462,"remaining_time":20.24429184},
{"learn":[0.2601513302],"iteration":289,"passed_time":8.26339234,"remaining_time":20.23106401},
{"learn":[0.2594447136],"iteration":290,"passed_time":8.29225964,"remaining_time":20.20347795},
{"learn":[0.2586208792],"iteration":291,"passed_time":8.318812207,"remaining_time":20.17027069},
{"learn":[0.2577636382],"iteration":292,"passed_time":8.353628455,"remaining_time":20.15704886},
{"learn":[0.256805476],"iteration":293,"passed_time":8.412955873,"remaining_time":20.20254029},
{"learn":[0.2564180599],"iteration":294,"passed_time":8.473164164,"remaining_time":20.24942622},
{"learn":[0.255773376],"iteration":295,"passed_time":8.518461253,"remaining_time":20.26012406},
{"learn":[0.2552208339],"iteration":296,"passed_time":8.567552179,"remaining_time":20.27942486},
{"learn":[0.254726466],"iteration":297,"passed_time":8.617882436,"remaining_time":20.30118614},
{"learn":[0.2541391148],"iteration":298,"passed_time":8.673019628,"remaining_time":20.33373498},
{"learn":[0.2535346817],"iteration":299,"passed_time":8.711955362,"remaining_time":20.32789585},
{"learn":[0.2529429267],"iteration":300,"passed_time":8.737692913,"remaining_time":20.2911872},
{"learn":[0.2525877953],"iteration":301,"passed_time":8.765309598,"remaining_time":20.25889437},
{"learn":[0.2521451501],"iteration":302,"passed_time":8.791431116,"remaining_time":20.22319303},
{"learn":[0.2516666581],"iteration":303,"passed_time":8.817611112,"remaining_time":20.1876886},
{"learn":[0.2509313471],"iteration":304,"passed_time":8.848482652,"remaining_time":20.16293588},
{"learn":[0.25048643],"iteration":305,"passed_time":8.876134426,"remaining_time":20.13084082},
{"learn":[0.2498345936],"iteration":306,"passed_time":8.909194379,"remaining_time":20.11098275},
{"learn":[0.2493030324],"iteration":307,"passed_time":8.96302714,"remaining_time":20.13771033},
{"learn":[0.2485619152],"iteration":308,"passed_time":8.997275928,"remaining_time":20.1201219},
{"learn":[0.2482648176],"iteration":309,"passed_time":9.030046065,"remaining_time":20.09913479},
{"learn":[0.2477848109],"iteration":310,"passed_time":9.063164725,"remaining_time":20.07884404},
{"learn":[0.2469804427],"iteration":311,"passed_time":9.092585949,"remaining_time":20.05031773},
{"learn":[0.246511235],"iteration":312,"passed_time":9.116879691,"remaining_time":20.01053146},
{"learn":[0.2457524187],"iteration":313,"passed_time":9.143156958,"remaining_time":19.9751773},
{"learn":[0.245169303],"iteration":314,"passed_time":9.168423864,"remaining_time":19.93768364},
{"learn":[0.2445578295],"iteration":315,"passed_time":9.192309651,"remaining_time":19.89727785},
{"learn":[0.2439038613],"iteration":316,"passed_time":9.21621728,"remaining_time":19.85702335},
{"learn":[0.2434744554],"iteration":317,"passed_time":9.241204935,"remaining_time":19.81918794},
{"learn":[0.2428786895],"iteration":318,"passed_time":9.28179101,"remaining_time":19.81473253},
{"learn":[0.2422766125],"iteration":319,"passed_time":9.30896351,"remaining_time":19.78154746},
{"learn":[0.241874807],"iteration":320,"passed_time":9.34008677,"remaining_time":19.75675675},
{"learn":[0.2412712714],"iteration":321,"passed_time":9.369372024,"remaining_time":19.72805662},
{"learn":[0.2408264385],"iteration":322,"passed_time":9.39644057,"remaining_time":19.6947067},
{"learn":[0.2402237443],"iteration":323,"passed_time":9.42693159,"remaining_time":19.66853628},
{"learn":[0.2397459535],"iteration":324,"passed_time":9.465622886,"remaining_time":19.65937061},
{"learn":[0.2393519458],"iteration":325,"passed_time":9.492472216,"remaining_time":19.62554072},
{"learn":[0.2387610604],"iteration":326,"passed_time":9.523822728,"remaining_time":19.60101742},
{"learn":[0.238138311],"iteration":327,"passed_time":9.552411609,"remaining_time":19.57079452},
{"learn":[0.2377140382],"iteration":328,"passed_time":9.579627498,"remaining_time":19.53778131},
{"learn":[0.2371594205],"iteration":329,"passed_time":9.60434072,"remaining_time":19.49972207},
{"learn":[0.2366112821],"iteration":330,"passed_time":9.629220136,"remaining_time":19.46207937},
{"learn":[0.2361892251],"iteration":331,"passed_time":9.657657859,"remaining_time":19.43167304},
{"learn":[0.2353560504],"iteration":332,"passed_time":9.734174172,"remaining_time":19.4975801},
{"learn":[0.2349107125],"iteration":333,"passed_time":9.853739305,"remaining_time":19.64847418},
{"learn":[0.2344647576],"iteration":334,"passed_time":9.919478991,"remaining_time":19.69090606},
{"learn":[0.2338667337],"iteration":335,"passed_time":9.966538658,"remaining_time":19.69577878},
{"learn":[0.2332557089],"iteration":336,"passed_time":10.01197937,"remaining_time":19.69715824},
{"learn":[0.2326493824],"iteration":337,"passed_time":10.06004949,"remaining_time":19.70341053},
{"learn":[0.2322893143],"iteration":338,"passed_time":10.10315963,"remaining_time":19.69967114},
{"learn":[0.2317173902],"iteration":339,"passed_time":10.1509059,"remaining_time":19.70469969},
{"learn":[0.2311388044],"iteration":340,"passed_time":10.24617509,"remaining_time":19.80125919},
{"learn":[0.2306063596],"iteration":341,"passed_time":10.36205827,"remaining_time":19.93635773},
{"learn":[0.2301524667],"iteration":342,"passed_time":10.40678859,"remaining_time":19.93370293},
{"learn":[0.2297036508],"iteration":343,"passed_time":10.59056329,"remaining_time":20.1959579},
{"learn":[0.2290034014],"iteration":344,"passed_time":10.7059498,"remaining_time":20.32578876},
{"learn":[0.2282146566],"iteration":345,"passed_time":10.78859887,"remaining_time":20.39232272},
{"learn":[0.2278086157],"iteration":346,"passed_time":10.85282468,"remaining_time":20.42332713},
{"learn":[0.226997123],"iteration":347,"passed_time":10.88753967,"remaining_time":20.39849387},
{"learn":[0.2263524673],"iteration":348,"passed_time":10.92634965,"remaining_time":20.38124247},
{"learn":[0.2257369406],"iteration":349,"passed_time":11.04027422,"remaining_time":20.5033664},
{"learn":[0.2253296796],"iteration":350,"passed_time":11.08538308,"remaining_time":20.49690489},
{"learn":[0.2248026062],"iteration":351,"passed_time":11.12596599,"remaining_time":20.48189193},
{"learn":[0.2244312903],"iteration":352,"passed_time":11.16278257,"remaining_time":20.45983095},
{"learn":[0.2240106078],"iteration":353,"passed_time":11.19084324,"remaining_time":20.42170828},
{"learn":[0.2233888121],"iteration":354,"passed_time":11.2193432,"remaining_time":20.38444047},
{"learn":[0.2228412348],"iteration":355,"passed_time":11.25026724,"remaining_time":20.35160704},
{"learn":[0.2222420889],"iteration":356,"passed_time":11.28070006,"remaining_time":20.31789954},
{"learn":[0.2218568886],"iteration":357,"passed_time":11.33177163,"remaining_time":20.32122175},
{"learn":[0.2213014014],"iteration":358,"passed_time":11.35896073,"remaining_time":20.2815984},
{"learn":[0.2208299076],"iteration":359,"passed_time":11.38693583,"remaining_time":20.24344148},
{"learn":[0.2206523839],"iteration":360,"passed_time":11.41511307,"remaining_time":20.20569876},
{"learn":[0.2203001135],"iteration":361,"passed_time":11.44635031,"remaining_time":20.17340194},
{"learn":[0.2197508111],"iteration":362,"passed_time":11.47497782,"remaining_time":20.13653133},
{"learn":[0.2192946322],"iteration":363,"passed_time":11.50313322,"remaining_time":20.09888112},
{"learn":[0.2186225162],"iteration":364,"passed_time":11.54205068,"remaining_time":20.08000597},
{"learn":[0.2180458237],"iteration":365,"passed_time":11.58160623,"remaining_time":20.06212664},
{"learn":[0.2174951329],"iteration":366,"passed_time":11.60865573,"remaining_time":20.0225588},
{"learn":[0.2169634595],"iteration":367,"passed_time":11.63579854,"remaining_time":19.98321923},
{"learn":[0.2165425244],"iteration":368,"passed_time":11.66251178,"remaining_time":19.94321121},
{"learn":[0.2159406297],"iteration":369,"passed_time":11.69262378,"remaining_time":19.90906212},
{"learn":[0.2155675047],"iteration":370,"passed_time":11.71662439,"remaining_time":19.86457343},
{"learn":[0.215333013],"iteration":371,"passed_time":11.74362227,"remaining_time":19.82525479},
{"learn":[0.2150047947],"iteration":372,"passed_time":11.77751211,"remaining_time":19.79758737},
{"learn":[0.2146458345],"iteration":373,"passed_time":11.80772444,"remaining_time":19.76373129},
{"learn":[0.2141873135],"iteration":374,"passed_time":11.83470587,"remaining_time":19.72450979},
{"learn":[0.2138742138],"iteration":375,"passed_time":11.86005417,"remaining_time":19.68264308},
{"learn":[0.2133974468],"iteration":376,"passed_time":11.89217588,"remaining_time":19.65205722},
{"learn":[0.2127803494],"iteration":377,"passed_time":11.92965387,"remaining_time":19.63027701},
{"learn":[0.2125385649],"iteration":378,"passed_time":11.9576872,"remaining_time":19.59293866},
{"learn":[0.2120729054],"iteration":379,"passed_time":11.98923834,"remaining_time":19.56138887},
{"learn":[0.2117316583],"iteration":380,"passed_time":12.01615147,"remaining_time":19.52230384},
{"learn":[0.2111051924],"iteration":381,"passed_time":12.03902558,"remaining_time":19.47674818},
{"learn":[0.2108209834],"iteration":382,"passed_time":12.06533427,"remaining_time":19.43684398},
{"learn":[0.2104218988],"iteration":383,"passed_time":12.09187293,"remaining_time":19.39737949},
{"learn":[0.209956646],"iteration":384,"passed_time":12.11867753,"remaining_time":19.35840696},
{"learn":[0.2094990786],"iteration":385,"passed_time":12.1425898,"remaining_time":19.31489673},
{"learn":[0.209121087],"iteration":386,"passed_time":12.16892155,"remaining_time":19.27532018},
{"learn":[0.2086055419],"iteration":387,"passed_time":12.19780029,"remaining_time":19.23982933},
{"learn":[0.2079748546],"iteration":388,"passed_time":12.22457158,"remaining_time":19.20106231},
{"learn":[0.2074677804],"iteration":389,"passed_time":12.25016535,"remaining_time":19.16051504},
{"learn":[0.2070525254],"iteration":390,"passed_time":12.2806164,"remaining_time":19.12760969},
{"learn":[0.2064490599],"iteration":391,"passed_time":12.30569716,"remaining_time":19.08638743},
{"learn":[0.2060382226],"iteration":392,"passed_time":12.33700157,"remaining_time":19.05485993},
{"learn":[0.205542887],"iteration":393,"passed_time":12.36352323,"remaining_time":19.01597735},
{"learn":[0.2053057166],"iteration":394,"passed_time":12.39671533,"remaining_time":18.98737411},
{"learn":[0.2049863479],"iteration":395,"passed_time":12.42724912,"remaining_time":18.95469311},
{"learn":[0.2043765853],"iteration":396,"passed_time":12.45099517,"remaining_time":18.91171307},
{"learn":[0.2039930259],"iteration":397,"passed_time":12.47578993,"remaining_time":18.87041593},
{"learn":[0.2034803699],"iteration":398,"passed_time":12.50326958,"remaining_time":18.83324566},
{"learn":[0.2029382201],"iteration":399,"passed_time":12.53139758,"remaining_time":18.79709637},
{"learn":[0.2025270322],"iteration":400,"passed_time":12.55721055,"remaining_time":18.75752897},
{"learn":[0.202054767],"iteration":401,"passed_time":12.58084463,"remaining_time":18.71478878},
{"learn":[0.2014381745],"iteration":402,"passed_time":12.60775411,"remaining_time":18.67699555},
{"learn":[0.2010145468],"iteration":403,"passed_time":12.63528493,"remaining_time":18.64017282},
{"learn":[0.2007911346],"iteration":404,"passed_time":12.66653271,"remaining_time":18.6088567},
{"learn":[0.2005921532],"iteration":405,"passed_time":12.69250526,"remaining_time":18.56982297},
{"learn":[0.2001241516],"iteration":406,"passed_time":12.71881351,"remaining_time":18.53134253},
{"learn":[0.1997209857],"iteration":407,"passed_time":12.7476792,"remaining_time":18.49663257},
{"learn":[0.1993961334],"iteration":408,"passed_time":12.77263981,"remaining_time":18.45630839},
{"learn":[0.1986884229],"iteration":409,"passed_time":12.79975707,"remaining_time":18.41916261},
{"learn":[0.1983828404],"iteration":410,"passed_time":12.82708566,"remaining_time":18.3823685},
{"learn":[0.1979850741],"iteration":411,"passed_time":12.85092779,"remaining_time":18.34064452},
{"learn":[0.1976812727],"iteration":412,"passed_time":12.87413539,"remaining_time":18.29810526},
{"learn":[0.1973493239],"iteration":413,"passed_time":12.8978218,"remaining_time":18.25633713},
{"learn":[0.1968586024],"iteration":414,"passed_time":12.92551471,"remaining_time":18.22030386},
{"learn":[0.1964198561],"iteration":415,"passed_time":12.95205368,"remaining_time":18.18269074},
{"learn":[0.1959704371],"iteration":416,"passed_time":12.97683107,"remaining_time":18.14266789},
{"learn":[0.1953714034],"iteration":417,"passed_time":13.00764474,"remaining_time":18.11112258},
{"learn":[0.1948609773],"iteration":418,"passed_time":13.04269416,"remaining_time":18.08545419},
{"learn":[0.1946032188],"iteration":419,"passed_time":13.07477894,"remaining_time":18.05564711},
{"learn":[0.1940944756],"iteration":420,"passed_time":13.1063236,"remaining_time":18.02508638},
{"learn":[0.1938159606],"iteration":421,"passed_time":13.13377877,"remaining_time":17.98891974},
{"learn":[0.193210125],"iteration":422,"passed_time":13.15974518,"remaining_time":17.95076352},
{"learn":[0.192810844],"iteration":423,"passed_time":13.18366305,"remaining_time":17.90988188},
{"learn":[0.1924616169],"iteration":424,"passed_time":13.21634687,"remaining_time":17.88093988},
{"learn":[0.1921714334],"iteration":425,"passed_time":13.2459495,"remaining_time":17.84782867},
{"learn":[0.1916535041],"iteration":426,"passed_time":13.27629572,"remaining_time":17.81573173},
{"learn":[0.1913722824],"iteration":427,"passed_time":13.30376951,"remaining_time":17.77980411},
{"learn":[0.1908416608],"iteration":428,"passed_time":13.33788582,"remaining_time":17.75275712},
{"learn":[0.190572921],"iteration":429,"passed_time":13.36820352,"remaining_time":17.72064187},
{"learn":[0.1903355262],"iteration":430,"passed_time":13.39644801,"remaining_time":17.68579795},
{"learn":[0.1899970419],"iteration":431,"passed_time":13.42092123,"remaining_time":17.64602606},
{"learn":[0.1894726473],"iteration":432,"passed_time":13.44743014,"remaining_time":17.60899051},
{"learn":[0.1891952402],"iteration":433,"passed_time":13.47091232,"remaining_time":17.56805617},
{"learn":[0.1886445494],"iteration":434,"passed_time":13.49504118,"remaining_time":17.528042},
{"learn":[0.1883038914],"iteration":435,"passed_time":13.51895928,"remaining_time":17.48782806},
{"learn":[0.1879817738],"iteration":436,"passed_time":13.54278672,"remaining_time":17.44757191},
{"learn":[0.1873569629],"iteration":437,"passed_time":13.56794471,"remaining_time":17.40909801},
{"learn":[0.1869813975],"iteration":438,"passed_time":13.59276513,"remaining_time":17.3702534},
{"learn":[0.1865270418],"iteration":439,"passed_time":13.6156291,"remaining_time":17.32898249},
{"learn":[0.1863001234],"iteration":440,"passed_time":13.64476382,"remaining_time":17.2957437},
{"learn":[0.1860305281],"iteration":441,"passed_time":13.66964372,"remaining_time":17.25715202},
{"learn":[0.1858968875],"iteration":442,"passed_time":13.69428549,"remaining_time":17.21832284},
{"learn":[0.1856103504],"iteration":443,"passed_time":13.71695213,"remaining_time":17.17708421},
{"learn":[0.1852669435],"iteration":444,"passed_time":13.74100445,"remaining_time":17.13765724},
{"learn":[0.1850043746],"iteration":445,"passed_time":13.76580417,"remaining_time":17.0992276},
{"learn":[0.1844773293],"iteration":446,"passed_time":13.79051925,"remaining_time":17.06075424},
{"learn":[0.1839785716],"iteration":447,"passed_time":13.81401248,"remaining_time":17.02083681},
{"learn":[0.1836537614],"iteration":448,"passed_time":13.83934019,"remaining_time":16.98324376},
{"learn":[0.1832389271],"iteration":449,"passed_time":13.86167486,"remaining_time":16.94204705},
{"learn":[0.1828548487],"iteration":450,"passed_time":13.88816622,"remaining_time":16.90599391},
{"learn":[0.1826634127],"iteration":451,"passed_time":13.9133389,"remaining_time":16.86838433},
{"learn":[0.1823653333],"iteration":452,"passed_time":13.94213513,"remaining_time":16.83520511},
{"learn":[0.1818776692],"iteration":453,"passed_time":13.96977214,"remaining_time":16.80065108},
{"learn":[0.1816752658],"iteration":454,"passed_time":13.99411429,"remaining_time":16.76218085},
{"learn":[0.1810927672],"iteration":455,"passed_time":14.0182309,"remaining_time":16.72350354},
{"learn":[0.1807855157],"iteration":456,"passed_time":14.04294603,"remaining_time":16.68560109},
{"learn":[0.1803880018],"iteration":457,"passed_time":14.07175745,"remaining_time":16.6526038},
{"learn":[0.180055997],"iteration":458,"passed_time":14.09689072,"remaining_time":16.6152895},
{"learn":[0.1797830217],"iteration":459,"passed_time":14.12214468,"remaining_time":16.57816984},
{"learn":[0.1795912069],"iteration":460,"passed_time":14.14599692,"remaining_time":16.53946278},
{"learn":[0.1791238925],"iteration":461,"passed_time":14.17013515,"remaining_time":16.50115306},
{"learn":[0.1788791628],"iteration":462,"passed_time":14.19478655,"remaining_time":16.46349973},
{"learn":[0.1785094037],"iteration":463,"passed_time":14.21987033,"remaining_time":16.42640193},
{"learn":[0.1782503549],"iteration":464,"passed_time":14.24301657,"remaining_time":16.38712659},
{"learn":[0.1779266806],"iteration":465,"passed_time":14.26646473,"remaining_time":16.34826645},
{"learn":[0.1776089949],"iteration":466,"passed_time":14.28962912,"remaining_time":16.30914844},
{"learn":[0.1771124391],"iteration":467,"passed_time":14.31530266,"remaining_time":16.27295089},
{"learn":[0.1768161549],"iteration":468,"passed_time":14.34017346,"remaining_time":16.23588936},
{"learn":[0.1764065799],"iteration":469,"passed_time":14.36793568,"remaining_time":16.20214023},
{"learn":[0.1760684743],"iteration":470,"passed_time":14.39194342,"remaining_time":16.16419972},
{"learn":[0.1757900014],"iteration":471,"passed_time":14.41872706,"remaining_time":16.12942349},
{"learn":[0.1754295125],"iteration":472,"passed_time":14.44307429,"remaining_time":16.09196649},
{"learn":[0.1749926455],"iteration":473,"passed_time":14.46567076,"remaining_time":16.05262199},
{"learn":[0.1745876705],"iteration":474,"passed_time":14.49676193,"remaining_time":16.02273687},
{"learn":[0.1740663893],"iteration":475,"passed_time":14.52078528,"remaining_time":15.98506615},
{"learn":[0.1737969342],"iteration":476,"passed_time":14.54611626,"remaining_time":15.94888638},
{"learn":[0.1734048479],"iteration":477,"passed_time":14.5713118,"remaining_time":15.9126041},
{"learn":[0.1731657281],"iteration":478,"passed_time":14.60083,"remaining_time":15.8810698},
{"learn":[0.1728115783],"iteration":479,"passed_time":14.63409886,"remaining_time":15.8536071},
{"learn":[0.1725040043],"iteration":480,"passed_time":14.66714946,"remaining_time":15.82588476},
{"learn":[0.1723254428],"iteration":481,"passed_time":14.69744267,"remaining_time":15.79517698},
{"learn":[0.1721074441],"iteration":482,"passed_time":14.72813424,"remaining_time":15.76489731},
{"learn":[0.1717376148],"iteration":483,"passed_time":14.75874111,"remaining_time":15.73452565},
{"learn":[0.1714368988],"iteration":484,"passed_time":14.78488776,"remaining_time":15.6994169},
{"learn":[0.1711778641],"iteration":485,"passed_time":14.81573992,"remaining_time":15.66932164},
{"learn":[0.1708378511],"iteration":486,"passed_time":14.84142676,"remaining_time":15.6337822},
{"learn":[0.1703560493],"iteration":487,"passed_time":14.86553836,"remaining_time":15.59663041},
{"learn":[0.1701584844],"iteration":488,"passed_time":14.89355263,"remaining_time":15.56361022},
{"learn":[0.1697821617],"iteration":489,"passed_time":14.92644959,"remaining_time":15.53569243},
{"learn":[0.169409836],"iteration":490,"passed_time":14.95041992,"remaining_time":15.49850049},
{"learn":[0.1690512545],"iteration":491,"passed_time":14.97752145,"remaining_time":15.46459532},
{"learn":[0.1687412963],"iteration":492,"passed_time":15.0018823,"remaining_time":15.42789925},
{"learn":[0.1685158786],"iteration":493,"passed_time":15.02711686,"remaining_time":15.39214803},
{"learn":[0.1682395935],"iteration":494,"passed_time":15.05163837,"remaining_time":15.35571188},
{"learn":[0.1679430008],"iteration":495,"passed_time":15.07586222,"remaining_time":15.31902129},
{"learn":[0.1677214538],"iteration":496,"passed_time":15.09938108,"remaining_time":15.28166737},
{"learn":[0.167329101],"iteration":497,"passed_time":15.12420211,"remaining_time":15.24568165},
{"learn":[0.1670519043],"iteration":498,"passed_time":15.14768487,"remaining_time":15.20839704},
{"learn":[0.1668646616],"iteration":499,"passed_time":15.17055396,"remaining_time":15.17055396},
{"learn":[0.1664994745],"iteration":500,"passed_time":15.19379844,"remaining_time":15.13314456},
{"learn":[0.166241744],"iteration":501,"passed_time":15.21744956,"remaining_time":15.09619498},
{"learn":[0.1659166532],"iteration":502,"passed_time":15.24272803,"remaining_time":15.06090623},
{"learn":[0.1656128659],"iteration":503,"passed_time":15.26715066,"remaining_time":15.02481494},
{"learn":[0.1653350522],"iteration":504,"passed_time":15.29002164,"remaining_time":14.98724894},
{"learn":[0.164971562],"iteration":505,"passed_time":15.31850034,"remaining_time":14.95521575},
{"learn":[0.1646808596],"iteration":506,"passed_time":15.34733698,"remaining_time":14.92354464},
{"learn":[0.164435036],"iteration":507,"passed_time":15.37667137,"remaining_time":14.89236676},
{"learn":[0.16410693],"iteration":508,"passed_time":15.40218893,"remaining_time":14.85751427},
{"learn":[0.163867109],"iteration":509,"passed_time":15.42707633,"remaining_time":14.82209294},
{"learn":[0.16356356],"iteration":510,"passed_time":15.45235204,"remaining_time":14.78708443},
{"learn":[0.1631724414],"iteration":511,"passed_time":15.47965659,"remaining_time":14.75404769},
{"learn":[0.1627611974],"iteration":512,"passed_time":15.50894888,"remaining_time":14.72292029},
{"learn":[0.1624887691],"iteration":513,"passed_time":15.55486078,"remaining_time":14.70751428},
{"learn":[0.1622190896],"iteration":514,"passed_time":15.59887694,"remaining_time":14.69020449},
{"learn":[0.1620249468],"iteration":515,"passed_time":15.63272071,"remaining_time":14.66324965},
{"learn":[0.1617923063],"iteration":516,"passed_time":15.67832396,"remaining_time":14.6472543},
{"learn":[0.1615647989],"iteration":517,"passed_time":15.70338704,"remaining_time":14.61203196},
{"learn":[0.1612244774],"iteration":518,"passed_time":15.74248686,"remaining_time":14.58985776},
{"learn":[0.1609598048],"iteration":519,"passed_time":15.76791885,"remaining_time":14.55500201},
{"learn":[0.1607874281],"iteration":520,"passed_time":15.79778221,"remaining_time":14.52425658},
{"learn":[0.1605003161],"iteration":521,"passed_time":15.82751285,"remaining_time":14.49339299},
{"learn":[0.1602146345],"iteration":522,"passed_time":15.89878524,"remaining_time":14.50042172},
{"learn":[0.1598546926],"iteration":523,"passed_time":16.18821226,"remaining_time":14.70532259},
{"learn":[0.1595831478],"iteration":524,"passed_time":16.3210452,"remaining_time":14.76665995},
{"learn":[0.15940669],"iteration":525,"passed_time":16.35536696,"remaining_time":14.73848657},
{"learn":[0.1589849416],"iteration":526,"passed_time":16.39163901,"remaining_time":14.71204032},
{"learn":[0.158823406],"iteration":527,"passed_time":16.42737202,"remaining_time":14.68507499},
{"learn":[0.1584584713],"iteration":528,"passed_time":16.45480935,"remaining_time":14.65069037},
{"learn":[0.1580918536],"iteration":529,"passed_time":16.48010191,"remaining_time":14.61443},
{"learn":[0.1577367923],"iteration":530,"passed_time":16.50640738,"remaining_time":14.57910558},
{"learn":[0.1575203783],"iteration":531,"passed_time":16.53546791,"remaining_time":14.54623869},
{"learn":[0.1573216775],"iteration":532,"passed_time":16.56026577,"remaining_time":14.50965125},
{"learn":[0.1569869098],"iteration":533,"passed_time":16.58744041,"remaining_time":14.47518208},
{"learn":[0.1568367341],"iteration":534,"passed_time":16.61582794,"remaining_time":14.44179438},
{"learn":[0.15663391],"iteration":535,"passed_time":16.65053682,"remaining_time":14.41389754},
{"learn":[0.1563230122],"iteration":536,"passed_time":16.68672794,"remaining_time":14.38725333},
{"learn":[0.1560204871],"iteration":537,"passed_time":16.71723655,"remaining_time":14.35569384},
{"learn":[0.155738494],"iteration":538,"passed_time":16.7488248,"remaining_time":14.32506166},
{"learn":[0.1555693009],"iteration":539,"passed_time":16.77946604,"remaining_time":14.29361922},
{"learn":[0.1554367683],"iteration":540,"passed_time":16.80977864,"remaining_time":14.26190092},
{"learn":[0.1550902198],"iteration":541,"passed_time":16.8408996,"remaining_time":14.23087088},
{"learn":[0.1548765687],"iteration":542,"passed_time":16.87904686,"remaining_time":14.20575398},
{"learn":[0.1544423103],"iteration":543,"passed_time":16.91839272,"remaining_time":14.1815939},
{"learn":[0.1540034378],"iteration":544,"passed_time":16.95419258,"remaining_time":14.15441766},
{"learn":[0.153732959],"iteration":545,"passed_time":16.98630796,"remaining_time":14.12414618},
{"learn":[0.1533288956],"iteration":546,"passed_time":17.01767514,"remaining_time":14.09324833},
{"learn":[0.1529312835],"iteration":547,"passed_time":17.05032393,"remaining_time":14.06340587},
{"learn":[0.1525195206],"iteration":548,"passed_time":17.08491733,"remaining_time":14.03515067},
{"learn":[0.1520710412],"iteration":549,"passed_time":17.12098833,"remaining_time":14.00808136},
{"learn":[0.1518783149],"iteration":550,"passed_time":17.14668674,"remaining_time":13.97252694},
{"learn":[0.1515846252],"iteration":551,"passed_time":17.17877969,"remaining_time":13.94219801},
{"learn":[0.1513445658],"iteration":552,"passed_time":17.20819944,"remaining_time":13.9097019},
{"learn":[0.1510654197],"iteration":553,"passed_time":17.23685579,"remaining_time":13.87660232},
{"learn":[0.1508040709],"iteration":554,"passed_time":17.26292771,"remaining_time":13.84144654},
{"learn":[0.1504354477],"iteration":555,"passed_time":17.29126915,"remaining_time":13.8081358},
{"learn":[0.150117229],"iteration":556,"passed_time":17.31859989,"remaining_time":13.77403905},
{"learn":[0.1498323609],"iteration":557,"passed_time":17.34840113,"remaining_time":13.74192348},
{"learn":[0.1495723865],"iteration":558,"passed_time":17.37579441,"remaining_time":13.70791652},
{"learn":[0.1492870555],"iteration":559,"passed_time":17.40697178,"remaining_time":13.6769064},
{"learn":[0.149169445],"iteration":560,"passed_time":17.43253121,"remaining_time":13.64149947},
{"learn":[0.1489261459],"iteration":561,"passed_time":17.45894422,"remaining_time":13.60679283},
{"learn":[0.1488144818],"iteration":562,"passed_time":17.49943792,"remaining_time":13.58304506},
{"learn":[0.1485766383],"iteration":563,"passed_time":17.55555535,"remaining_time":13.57131584},
{"learn":[0.1482474103],"iteration":564,"passed_time":17.62140549,"remaining_time":13.56692281},
{"learn":[0.1480191736],"iteration":565,"passed_time":17.65557213,"remaining_time":13.5380182},
{"learn":[0.1477547253],"iteration":566,"passed_time":17.68800109,"remaining_time":13.50776803},
{"learn":[0.1474451598],"iteration":567,"passed_time":17.71683689,"remaining_time":13.47477735},
{"learn":[0.1470224156],"iteration":568,"passed_time":17.75330332,"remaining_time":13.44758125},
{"learn":[0.1467459763],"iteration":569,"passed_time":17.79675537,"remaining_time":13.42562247},
{"learn":[0.1464999003],"iteration":570,"passed_time":17.84993443,"remaining_time":13.41089645},
{"learn":[0.1463384208],"iteration":571,"passed_time":17.89923224,"remaining_time":13.39313182},
{"learn":[0.1461687369],"iteration":572,"passed_time":17.93294366,"remaining_time":13.36364213},
{"learn":[0.1459576523],"iteration":573,"passed_time":17.96633871,"remaining_time":13.33390295},
{"learn":[0.1456802873],"iteration":574,"passed_time":17.99310681,"remaining_time":13.29925286},
{"learn":[0.1454175641],"iteration":575,"passed_time":18.01777413,"remaining_time":13.26308374},
{"learn":[0.145163508],"iteration":576,"passed_time":18.04356203,"remaining_time":13.22777598},
{"learn":[0.1449913698],"iteration":577,"passed_time":18.08699344,"remaining_time":13.20538275},
{"learn":[0.144790425],"iteration":578,"passed_time":18.14650636,"remaining_time":13.19460998},
{"learn":[0.1444193616],"iteration":579,"passed_time":18.20496332,"remaining_time":13.18290448},
{"learn":[0.144136527],"iteration":580,"passed_time":18.2393317,"remaining_time":13.15366606},
{"learn":[0.1438882772],"iteration":581,"passed_time":18.26858708,"remaining_time":13.1207378},
{"learn":[0.1436877671],"iteration":582,"passed_time":18.29390651,"remaining_time":13.08500689},
{"learn":[0.1435808013],"iteration":583,"passed_time":18.33331326,"remaining_time":13.05934643},
{"learn":[0.143470091],"iteration":584,"passed_time":18.37727336,"remaining_time":13.03686914},
{"learn":[0.1431945773],"iteration":585,"passed_time":18.41589309,"remaining_time":13.01054563},
{"learn":[0.1429781353],"iteration":586,"passed_time":18.45399988,"remaining_time":12.98381933},
{"learn":[0.1426614453],"iteration":587,"passed_time":18.48604385,"remaining_time":12.95280623},
{"learn":[0.1422627673],"iteration":588,"passed_time":18.5215272,"remaining_time":12.92418961},
{"learn":[0.1419780815],"iteration":589,"passed_time":18.55283314,"remaining_time":12.89264676},
{"learn":[0.1417816667],"iteration":590,"passed_time":18.58644735,"remaining_time":12.86270214},
{"learn":[0.1415206545],"iteration":591,"passed_time":18.61947049,"remaining_time":12.83233777},
{"learn":[0.1413288397],"iteration":592,"passed_time":18.65671561,"remaining_time":12.80486214},
{"learn":[0.1411301529],"iteration":593,"passed_time":18.6906946,"remaining_time":12.77512123},
{"learn":[0.1407863954],"iteration":594,"passed_time":18.72337889,"remaining_time":12.74448479},
{"learn":[0.1404621461],"iteration":595,"passed_time":18.75468692,"remaining_time":12.71290859},
{"learn":[0.1402829395],"iteration":596,"passed_time":18.78891209,"remaining_time":12.68330246},
{"learn":[0.1399867955],"iteration":597,"passed_time":18.82199672,"remaining_time":12.65291418},
{"learn":[0.1397308742],"iteration":598,"passed_time":18.8477382,"remaining_time":12.61760103},
{"learn":[0.1393527424],"iteration":599,"passed_time":18.87114533,"remaining_time":12.58076355},
{"learn":[0.1392020338],"iteration":600,"passed_time":18.89984225,"remaining_time":12.54748262},
{"learn":[0.1388150944],"iteration":601,"passed_time":18.92896777,"remaining_time":12.51450029},
{"learn":[0.138690107],"iteration":602,"passed_time":18.96361068,"remaining_time":12.48516325},
{"learn":[0.138438926],"iteration":603,"passed_time":19.00148467,"remaining_time":12.45792703},
{"learn":[0.1381894841],"iteration":604,"passed_time":19.05186084,"remaining_time":12.43881824},
{"learn":[0.1380217075],"iteration":605,"passed_time":19.08555946,"remaining_time":12.40876308},
{"learn":[0.1377312436],"iteration":606,"passed_time":19.11809692,"remaining_time":12.37794413},
{"learn":[0.1374050729],"iteration":607,"passed_time":19.14880723,"remaining_time":12.34594151},
{"learn":[0.1371167968],"iteration":608,"passed_time":19.1719207,"remaining_time":12.30906567},
{"learn":[0.1368369635],"iteration":609,"passed_time":19.1978996,"remaining_time":12.27406696},
{"learn":[0.1366297217],"iteration":610,"passed_time":19.22076814,"remaining_time":12.23711752},
{"learn":[0.1363646002],"iteration":611,"passed_time":19.25716006,"remaining_time":12.20878775},
{"learn":[0.1361801484],"iteration":612,"passed_time":19.29176816,"remaining_time":12.17930551},
{"learn":[0.1359271442],"iteration":613,"passed_time":19.32521842,"remaining_time":12.14907868},
{"learn":[0.1358553382],"iteration":614,"passed_time":19.35673641,"remaining_time":12.11763173},
{"learn":[0.1356737053],"iteration":615,"passed_time":19.39281308,"remaining_time":12.08902634},
{"learn":[0.1354570108],"iteration":616,"passed_time":19.44041184,"remaining_time":12.067549},
{"learn":[0.1352208642],"iteration":617,"passed_time":19.48712759,"remaining_time":12.04544133},
{"learn":[0.1350883316],"iteration":618,"passed_time":19.52780216,"remaining_time":12.01953574},
{"learn":[0.1348827166],"iteration":619,"passed_time":19.56343706,"remaining_time":11.99049368},
{"learn":[0.1345562234],"iteration":620,"passed_time":19.6060717,"remaining_time":11.96570237},
{"learn":[0.1342818457],"iteration":621,"passed_time":19.6532369,"remaining_time":11.94360699},
{"learn":[0.1339884646],"iteration":622,"passed_time":19.68691898,"remaining_time":11.913272},
{"learn":[0.1337937327],"iteration":623,"passed_time":19.7204641,"remaining_time":11.88284375},
{"learn":[0.1336945646],"iteration":624,"passed_time":19.74638631,"remaining_time":11.84783178},
{"learn":[0.1333936242],"iteration":625,"passed_time":19.77283861,"remaining_time":11.81316556},
{"learn":[0.1330282828],"iteration":626,"passed_time":19.79941557,"remaining_time":11.77859969},
{"learn":[0.1327528393],"iteration":627,"passed_time":19.82299416,"remaining_time":11.74228317},
{"learn":[0.1324973948],"iteration":628,"passed_time":19.85569847,"remaining_time":11.71138972},
{"learn":[0.1323011202],"iteration":629,"passed_time":19.89113185,"remaining_time":11.68209331},
{"learn":[0.1319874595],"iteration":630,"passed_time":19.92438769,"remaining_time":11.65150405},
{"learn":[0.1317481995],"iteration":631,"passed_time":19.95774996,"remaining_time":11.62096833},
{"learn":[0.1314806377],"iteration":632,"passed_time":19.99116577,"remaining_time":11.59045472},
{"learn":[0.1312020386],"iteration":633,"passed_time":20.02837299,"remaining_time":11.56212069},
{"learn":[0.1308692764],"iteration":634,"passed_time":20.0639247,"remaining_time":11.53280711},
{"learn":[0.1306552747],"iteration":635,"passed_time":20.10240192,"remaining_time":11.50514827},
{"learn":[0.1304771059],"iteration":636,"passed_time":20.136652,"remaining_time":11.47504659},
{"learn":[0.130329665],"iteration":637,"passed_time":20.167422,"remaining_time":11.44295731},
{"learn":[0.1301035881],"iteration":638,"passed_time":20.20288046,"remaining_time":11.41352088},
{"learn":[0.1299256156],"iteration":639,"passed_time":20.24370874,"remaining_time":11.38708617},
{"learn":[0.129794822],"iteration":640,"passed_time":20.31327203,"remaining_time":11.37669994},
{"learn":[0.1295568242],"iteration":641,"passed_time":20.35319344,"remaining_time":11.34960008},
{"learn":[0.1294025253],"iteration":642,"passed_time":20.38856504,"remaining_time":11.31993425},
{"learn":[0.1290575336],"iteration":643,"passed_time":20.41721436,"remaining_time":11.28653465},
{"learn":[0.1287219665],"iteration":644,"passed_time":20.4466176,"remaining_time":11.25356473},
{"learn":[0.128426075],"iteration":645,"passed_time":20.46858906,"remaining_time":11.21653332},
{"learn":[0.1282183142],"iteration":646,"passed_time":20.49757159,"remaining_time":11.18337368},
{"learn":[0.1279744541],"iteration":647,"passed_time":20.52130407,"remaining_time":11.14737505},
{"learn":[0.1277817838],"iteration":648,"passed_time":20.54603317,"remaining_time":11.11195322},
{"learn":[0.1276137689],"iteration":649,"passed_time":20.56792163,"remaining_time":11.07503472},
{"learn":[0.1273751119],"iteration":650,"passed_time":20.60586296,"remaining_time":11.04676831},
{"learn":[0.1272065079],"iteration":651,"passed_time":20.66315321,"remaining_time":11.02879957},
{"learn":[0.1268835769],"iteration":652,"passed_time":20.70892878,"remaining_time":11.00459155},
{"learn":[0.1267262487],"iteration":653,"passed_time":20.75443558,"remaining_time":10.9801754},
{"learn":[0.1265799859],"iteration":654,"passed_time":20.77670765,"remaining_time":10.9434567},
{"learn":[0.1263587335],"iteration":655,"passed_time":20.80066884,"remaining_time":10.90766781},
{"learn":[0.1261222924],"iteration":656,"passed_time":20.82388921,"remaining_time":10.87152816},
{"learn":[0.125917042],"iteration":657,"passed_time":20.84865819,"remaining_time":10.83623268},
{"learn":[0.1258624021],"iteration":658,"passed_time":20.87132871,"remaining_time":10.79988329},
{"learn":[0.1255972806],"iteration":659,"passed_time":20.89396057,"remaining_time":10.76355544},
{"learn":[0.1253834051],"iteration":660,"passed_time":20.92270792,"remaining_time":10.73040543},
{"learn":[0.1251328272],"iteration":661,"passed_time":20.94512218,"remaining_time":10.69403519},
{"learn":[0.1250223833],"iteration":662,"passed_time":20.97143178,"remaining_time":10.65968704},
{"learn":[0.1249443222],"iteration":663,"passed_time":20.99414524,"remaining_time":10.62354338},
{"learn":[0.1248431486],"iteration":664,"passed_time":21.03732039,"remaining_time":10.59774787},
{"learn":[0.1246809539],"iteration":665,"passed_time":21.09380721,"remaining_time":10.57857599},
{"learn":[0.1244080207],"iteration":666,"passed_time":21.14250351,"remaining_time":10.5554028},
{"learn":[0.1241071645],"iteration":667,"passed_time":21.23503302,"remaining_time":10.55393857},
{"learn":[0.1239636365],"iteration":668,"passed_time":21.30795374,"remaining_time":10.54250028},
{"learn":[0.1237014602],"iteration":669,"passed_time":21.36716499,"remaining_time":10.52412604},
{"learn":[0.1235340904],"iteration":670,"passed_time":21.40560373,"remaining_time":10.49544505},
{"learn":[0.1233163721],"iteration":671,"passed_time":21.45452609,"remaining_time":10.47185202},
{"learn":[0.1231417936],"iteration":672,"passed_time":21.4848247,"remaining_time":10.43913473},
{"learn":[0.122984802],"iteration":673,"passed_time":21.53599283,"remaining_time":10.41651879},
{"learn":[0.1226991485],"iteration":674,"passed_time":21.58675851,"remaining_time":10.39362447},
{"learn":[0.122499494],"iteration":675,"passed_time":21.64215147,"remaining_time":10.3728655},
{"learn":[0.1223295156],"iteration":676,"passed_time":21.67456528,"remaining_time":10.34104075},
{"learn":[0.1221316001],"iteration":677,"passed_time":21.70046544,"remaining_time":10.30612076},
{"learn":[0.1219439226],"iteration":678,"passed_time":21.72695527,"remaining_time":10.2715061},
{"learn":[0.1217026991],"iteration":679,"passed_time":21.75189194,"remaining_time":10.23618444},
{"learn":[0.1214623451],"iteration":680,"passed_time":21.78450364,"remaining_time":10.20448849},
{"learn":[0.1214309861],"iteration":681,"passed_time":21.81227138,"remaining_time":10.17053123},
{"learn":[0.1211591468],"iteration":682,"passed_time":21.83841486,"remaining_time":10.13583823},
{"learn":[0.120994624],"iteration":683,"passed_time":21.86290078,"remaining_time":10.10040446},
{"learn":[0.1207733715],"iteration":684,"passed_time":21.88855951,"remaining_time":10.06554197},
{"learn":[0.1207373142],"iteration":685,"passed_time":21.9153053,"remaining_time":10.03120388},
{"learn":[0.1205512776],"iteration":686,"passed_time":21.94078501,"remaining_time":9.996311074},
{"learn":[0.120377765],"iteration":687,"passed_time":21.97091093,"remaining_time":9.963552631},
{"learn":[0.1202254856],"iteration":688,"passed_time":21.99896907,"remaining_time":9.929868475},
{"learn":[0.1200250738],"iteration":689,"passed_time":22.03894425,"remaining_time":9.901554664},
{"learn":[0.1197008806],"iteration":690,"passed_time":22.07446012,"remaining_time":9.87121299},
{"learn":[0.1195231606],"iteration":691,"passed_time":22.13568121,"remaining_time":9.852297418},
{"learn":[0.1193844992],"iteration":692,"passed_time":22.17509321,"remaining_time":9.823598292},
{"learn":[0.1193348099],"iteration":693,"passed_time":22.22367601,"remaining_time":9.798911902},
{"learn":[0.1190643872],"iteration":694,"passed_time":22.25304985,"remaining_time":9.765726912},
{"learn":[0.1188782524],"iteration":695,"passed_time":22.28245819,"remaining_time":9.732567947},
{"learn":[0.1186543633],"iteration":696,"passed_time":22.31804346,"remaining_time":9.702104978},
{"learn":[0.1184118776],"iteration":697,"passed_time":22.34624242,"remaining_time":9.668431533},
{"learn":[0.1182278745],"iteration":698,"passed_time":22.37320475,"remaining_time":9.634241242},
{"learn":[0.1181022279],"iteration":699,"passed_time":22.40102852,"remaining_time":9.600440795},
{"learn":[0.1179719532],"iteration":700,"passed_time":22.42814437,"remaining_time":9.566355443},
{"learn":[0.1176622896],"iteration":701,"passed_time":22.4542668,"remaining_time":9.531868243},
{"learn":[0.1173989212],"iteration":702,"passed_time":22.48241591,"remaining_time":9.49826106},
{"learn":[0.1172008234],"iteration":703,"passed_time":22.50585028,"remaining_time":9.462687051},
{"learn":[0.1170224442],"iteration":704,"passed_time":22.53447641,"remaining_time":9.429319917},
{"learn":[0.1167972018],"iteration":705,"passed_time":22.55977743,"remaining_time":9.394581538},
{"learn":[0.116457266],"iteration":706,"passed_time":22.58356564,"remaining_time":9.359242903},
{"learn":[0.1163936503],"iteration":707,"passed_time":22.60909558,"remaining_time":9.324655239},
{"learn":[0.1163626839],"iteration":708,"passed_time":22.64328626,"remaining_time":9.293647818},
{"learn":[0.1161579875],"iteration":709,"passed_time":22.66886173,"remaining_time":9.259112538},
{"learn":[0.1159836124],"iteration":710,"passed_time":22.69324571,"remaining_time":9.224118158},
{"learn":[0.1158540529],"iteration":711,"passed_time":22.71957305,"remaining_time":9.189939662},
{"learn":[0.1157053919],"iteration":712,"passed_time":22.74738172,"remaining_time":9.156379458},
{"learn":[0.1156117215],"iteration":713,"passed_time":22.77107908,"remaining_time":9.12118854},
{"learn":[0.1154267227],"iteration":714,"passed_time":22.79762425,"remaining_time":9.087164913},
{"learn":[0.1152272154],"iteration":715,"passed_time":22.8228334,"remaining_time":9.052632243},
{"learn":[0.1150780425],"iteration":716,"passed_time":22.84992205,"remaining_time":9.018867421},
{"learn":[0.1149304895],"iteration":717,"passed_time":22.87512833,"remaining_time":8.984381879},
{"learn":[0.1146975195],"iteration":718,"passed_time":22.90051815,"remaining_time":8.949993881},
{"learn":[0.1144764003],"iteration":719,"passed_time":22.92630931,"remaining_time":8.915786954},
{"learn":[0.1142909667],"iteration":720,"passed_time":22.95161945,"remaining_time":8.881417234},
{"learn":[0.1141622066],"iteration":721,"passed_time":22.97777623,"remaining_time":8.847398605},
{"learn":[0.1140579055],"iteration":722,"passed_time":23.00302964,"remaining_time":8.813055615},
{"learn":[0.1139466272],"iteration":723,"passed_time":23.03110676,"remaining_time":8.77981418},
{"learn":[0.1136718568],"iteration":724,"passed_time":23.07670581,"remaining_time":8.753233237},
{"learn":[0.1134882394],"iteration":725,"passed_time":23.1090506,"remaining_time":8.721597608},
{"learn":[0.1133276785],"iteration":726,"passed_time":23.13137359,"remaining_time":8.686196685},
{"learn":[0.1130580622],"iteration":727,"passed_time":23.15440386,"remaining_time":8.651095949},
{"learn":[0.1129304241],"iteration":728,"passed_time":23.17830118,"remaining_time":8.616350646},
{"learn":[0.1127473537],"iteration":729,"passed_time":23.20442985,"remaining_time":8.582460356},
{"learn":[0.1125949341],"iteration":730,"passed_time":23.22702009,"remaining_time":8.5472892},
{"learn":[0.1124532784],"iteration":731,"passed_time":23.2516677,"remaining_time":8.512905661},
{"learn":[0.1122691351],"iteration":732,"passed_time":23.27439529,"remaining_time":8.477849308},
{"learn":[0.1121183073],"iteration":733,"passed_time":23.29985964,"remaining_time":8.443818343},
{"learn":[0.1119015427],"iteration":734,"passed_time":23.32155759,"remaining_time":8.408452737},
{"learn":[0.111626008],"iteration":735,"passed_time":23.34783389,"remaining_time":8.374766505},
{"learn":[0.11141756],"iteration":736,"passed_time":23.36983077,"remaining_time":8.339573261},
{"learn":[0.1112463895],"iteration":737,"passed_time":23.39715085,"remaining_time":8.306305585},
{"learn":[0.1110712921],"iteration":738,"passed_time":23.41948156,"remaining_time":8.271291864},
{"learn":[0.110818933],"iteration":739,"passed_time":23.44286494,"remaining_time":8.236682275},
{"learn":[0.110633815],"iteration":740,"passed_time":23.47072632,"remaining_time":8.203668173},
{"learn":[0.1104495876],"iteration":741,"passed_time":23.50038284,"remaining_time":8.171292146},
{"learn":[0.1101935471],"iteration":742,"passed_time":23.52296206,"remaining_time":8.136475435},
{"learn":[0.1101074569],"iteration":743,"passed_time":23.54637835,"remaining_time":8.101979648},
{"learn":[0.1100209601],"iteration":744,"passed_time":23.56886572,"remaining_time":8.067195651},
{"learn":[0.1097829342],"iteration":745,"passed_time":23.59295177,"remaining_time":8.032988942},
{"learn":[0.1096127594],"iteration":746,"passed_time":23.61736889,"remaining_time":7.998921459},
{"learn":[0.1093723634],"iteration":747,"passed_time":23.64013313,"remaining_time":7.964322927},
{"learn":[0.1091564403],"iteration":748,"passed_time":23.663315,"remaining_time":7.929895949},
{"learn":[0.1090381356],"iteration":749,"passed_time":23.68618248,"remaining_time":7.89539416},
{"learn":[0.108760406],"iteration":750,"passed_time":23.71238621,"remaining_time":7.862029515},
{"learn":[0.1086199704],"iteration":751,"passed_time":23.73517999,"remaining_time":7.827559358},
{"learn":[0.1083914532],"iteration":752,"passed_time":23.75871565,"remaining_time":7.793363568},
{"learn":[0.1083073756],"iteration":753,"passed_time":23.78240902,"remaining_time":7.759247504},
{"learn":[0.1080967538],"iteration":754,"passed_time":23.80813998,"remaining_time":7.725820257},
{"learn":[0.1077895445],"iteration":755,"passed_time":23.83353364,"remaining_time":7.692304507},
{"learn":[0.1077101651],"iteration":756,"passed_time":23.856943,"remaining_time":7.65817325},
{"learn":[0.10752267],"iteration":757,"passed_time":23.88526464,"remaining_time":7.625638579},
{"learn":[0.1074089583],"iteration":758,"passed_time":23.90919453,"remaining_time":7.591720531},
{"learn":[0.1072342817],"iteration":759,"passed_time":23.9330531,"remaining_time":7.557806243},
{"learn":[0.1070169842],"iteration":760,"passed_time":23.95766605,"remaining_time":7.524155302},
{"learn":[0.1068089149],"iteration":761,"passed_time":23.9806018,"remaining_time":7.490004236},
{"learn":[0.1067052448],"iteration":762,"passed_time":24.00452888,"remaining_time":7.456190491},
{"learn":[0.1064605853],"iteration":763,"passed_time":24.02983651,"remaining_time":7.422829078},
{"learn":[0.1062499635],"iteration":764,"passed_time":24.05347924,"remaining_time":7.388977284},
{"learn":[0.1060610939],"iteration":765,"passed_time":24.07639621,"remaining_time":7.354930434},
{"learn":[0.1058626385],"iteration":766,"passed_time":24.09959685,"remaining_time":7.320998784},
{"learn":[0.1057813027],"iteration":767,"passed_time":24.12285014,"remaining_time":7.28711098},
{"learn":[0.105633932],"iteration":768,"passed_time":24.14746661,"remaining_time":7.25366032},
{"learn":[0.1055008383],"iteration":769,"passed_time":24.17151386,"remaining_time":7.220062581},
{"learn":[0.1053778564],"iteration":770,"passed_time":24.19580268,"remaining_time":7.186561367},
{"learn":[0.1051996876],"iteration":771,"passed_time":24.22032237,"remaining_time":7.153152201},
{"learn":[0.1050774069],"iteration":772,"passed_time":24.24533724,"remaining_time":7.119911452},
{"learn":[0.1049145881],"iteration":773,"passed_time":24.26982173,"remaining_time":7.086537093},
{"learn":[0.1047923986],"iteration":774,"passed_time":24.29911932,"remaining_time":7.054583029},
{"learn":[0.104636571],"iteration":775,"passed_time":24.32611721,"remaining_time":7.021971979},
{"learn":[0.1044139862],"iteration":776,"passed_time":24.35684784,"remaining_time":6.990446678},
{"learn":[0.1041479812],"iteration":777,"passed_time":24.38392191,"remaining_time":6.957880032},
{"learn":[0.1040081347],"iteration":778,"passed_time":24.40668041,"remaining_time":6.924103172},
{"learn":[0.1037968047],"iteration":779,"passed_time":24.43059398,"remaining_time":6.890680352},
{"learn":[0.1036918794],"iteration":780,"passed_time":24.4550058,"remaining_time":6.8574216},
{"learn":[0.1035547958],"iteration":781,"passed_time":24.4799497,"remaining_time":6.824333805},
{"learn":[0.1034606064],"iteration":782,"passed_time":24.50548981,"remaining_time":6.791432042},
{"learn":[0.1033481079],"iteration":783,"passed_time":24.52944395,"remaining_time":6.758112109},
{"learn":[0.1030704835],"iteration":784,"passed_time":24.55333452,"remaining_time":6.724798626},
{"learn":[0.1028743141],"iteration":785,"passed_time":24.57789653,"remaining_time":6.691691931},
{"learn":[0.1027265507],"iteration":786,"passed_time":24.60076546,"remaining_time":6.658148719},
{"learn":[0.1025400302],"iteration":787,"passed_time":24.62476106,"remaining_time":6.624935718},
{"learn":[0.1023834593],"iteration":788,"passed_time":24.64834934,"remaining_time":6.591637149},
{"learn":[0.1022581984],"iteration":789,"passed_time":24.67327372,"remaining_time":6.558718332},
{"learn":[0.1021114448],"iteration":790,"passed_time":24.69704792,"remaining_time":6.525515822},
{"learn":[0.1019188657],"iteration":791,"passed_time":24.72679108,"remaining_time":6.493904728},
{"learn":[0.1017205014],"iteration":792,"passed_time":24.74939519,"remaining_time":6.460434809},
{"learn":[0.1015272982],"iteration":793,"passed_time":24.77523215,"remaining_time":6.427831012},
{"learn":[0.1014045267],"iteration":794,"passed_time":24.79818286,"remaining_time":6.394499984},
{"learn":[0.1013629366],"iteration":795,"passed_time":24.82225059,"remaining_time":6.361481307},
{"learn":[0.1011534298],"iteration":796,"passed_time":24.84498355,"remaining_time":6.32814512},
{"learn":[0.1009573796],"iteration":797,"passed_time":24.86816198,"remaining_time":6.29494827},
{"learn":[0.1008725587],"iteration":798,"passed_time":24.89430623,"remaining_time":6.262522594},
{"learn":[0.1006706673],"iteration":799,"passed_time":24.91643183,"remaining_time":6.229107958},
{"learn":[0.1005094121],"iteration":800,"passed_time":24.94068641,"remaining_time":6.196250432},
{"learn":[0.1003599447],"iteration":801,"passed_time":24.96315906,"remaining_time":6.162974432},
{"learn":[0.1002546899],"iteration":802,"passed_time":24.98960025,"remaining_time":6.13069894},
{"learn":[0.09999571127],"iteration":803,"passed_time":25.01225004,"remaining_time":6.097513691},
{"learn":[0.0998580035],"iteration":804,"passed_time":25.03641785,"remaining_time":6.064722337},
{"learn":[0.09966466707],"iteration":805,"passed_time":25.06346331,"remaining_time":6.032645014},
{"learn":[0.09958676731],"iteration":806,"passed_time":25.09744267,"remaining_time":6.002238457},
{"learn":[0.0994570676],"iteration":807,"passed_time":25.13027124,"remaining_time":5.971549601},
{"learn":[0.09938704266],"iteration":808,"passed_time":25.17231731,"remaining_time":5.943031652},
{"learn":[0.0992428415],"iteration":809,"passed_time":25.1969847,"remaining_time":5.910403818},
{"learn":[0.09909142466],"iteration":810,"passed_time":25.2228576,"remaining_time":5.878076555},
{"learn":[0.09892226668],"iteration":811,"passed_time":25.24609081,"remaining_time":5.845154029},
{"learn":[0.09889125824],"iteration":812,"passed_time":25.27038455,"remaining_time":5.812499275},
{"learn":[0.09873177725],"iteration":813,"passed_time":25.29673621,"remaining_time":5.780335301},
{"learn":[0.09864717371],"iteration":814,"passed_time":25.31998438,"remaining_time":5.747481117},
{"learn":[0.09846192248],"iteration":815,"passed_time":25.34179325,"remaining_time":5.714325929},
{"learn":[0.09826547959],"iteration":816,"passed_time":25.36637023,"remaining_time":5.681818547},
{"learn":[0.09811139808],"iteration":817,"passed_time":25.39247279,"remaining_time":5.649669985},
{"learn":[0.0979477097],"iteration":818,"passed_time":25.41898251,"remaining_time":5.617626171},
{"learn":[0.09778408443],"iteration":819,"passed_time":25.44169849,"remaining_time":5.584763083},
{"learn":[0.09765922322],"iteration":820,"passed_time":25.46635283,"remaining_time":5.552347329},
{"learn":[0.09753297357],"iteration":821,"passed_time":25.4890864,"remaining_time":5.519534525},
{"learn":[0.09740318972],"iteration":822,"passed_time":25.51916273,"remaining_time":5.488325399},
{"learn":[0.09713623103],"iteration":823,"passed_time":25.54398383,"remaining_time":5.455996547},
{"learn":[0.09692685744],"iteration":824,"passed_time":25.57135863,"remaining_time":5.424227589},
{"learn":[0.09676290961],"iteration":825,"passed_time":25.59588428,"remaining_time":5.391869087},
{"learn":[0.09655261741],"iteration":826,"passed_time":25.62078721,"remaining_time":5.35960845},
{"learn":[0.09644587601],"iteration":827,"passed_time":25.64516089,"remaining_time":5.327255643},
{"learn":[0.09632908597],"iteration":828,"passed_time":25.66784335,"remaining_time":5.294573237},
{"learn":[0.09623710548],"iteration":829,"passed_time":25.69266953,"remaining_time":5.262354},
{"learn":[0.09606227454],"iteration":830,"passed_time":25.72083967,"remaining_time":5.230832615},
{"learn":[0.09598766355],"iteration":831,"passed_time":25.74813648,"remaining_time":5.199142942},
{"learn":[0.09587899376],"iteration":832,"passed_time":25.77172731,"remaining_time":5.166720842},
{"learn":[0.095801662],"iteration":833,"passed_time":25.7994245,"remaining_time":5.135137251},
{"learn":[0.0955841962],"iteration":834,"passed_time":25.82856745,"remaining_time":5.103848658},
{"learn":[0.0955247879],"iteration":835,"passed_time":25.85202165,"remaining_time":5.071449223},
{"learn":[0.09536827312],"iteration":836,"passed_time":25.88184606,"remaining_time":5.040311717},
{"learn":[0.09521300652],"iteration":837,"passed_time":25.90968665,"remaining_time":5.00879384},
{"learn":[0.09502604428],"iteration":838,"passed_time":25.94059576,"remaining_time":4.977873561},
{"learn":[0.09485905311],"iteration":839,"passed_time":25.96758978,"remaining_time":4.946207577},
{"learn":[0.0946633956],"iteration":840,"passed_time":25.99830831,"remaining_time":4.915256862},
{"learn":[0.09452514087],"iteration":841,"passed_time":26.02323517,"remaining_time":4.883219901},
{"learn":[0.09440572122],"iteration":842,"passed_time":26.04853213,"remaining_time":4.851268736},
{"learn":[0.09416037447],"iteration":843,"passed_time":26.07381219,"remaining_time":4.819330215},
{"learn":[0.09401781419],"iteration":844,"passed_time":26.10138579,"remaining_time":4.787828162},
{"learn":[0.09379022262],"iteration":845,"passed_time":26.12979154,"remaining_time":4.756486876},
{"learn":[0.09367508047],"iteration":846,"passed_time":26.16091509,"remaining_time":4.725643458},
{"learn":[0.09337672767],"iteration":847,"passed_time":26.19287263,"remaining_time":4.694948868},
{"learn":[0.0931133102],"iteration":848,"passed_time":26.2199686,"remaining_time":4.663386641},
{"learn":[0.09287878345],"iteration":849,"passed_time":26.26066277,"remaining_time":4.634234606},
{"learn":[0.09281441745],"iteration":850,"passed_time":26.3046466,"remaining_time":4.605631425},
{"learn":[0.09268363784],"iteration":851,"passed_time":26.34371906,"remaining_time":4.576138992},
{"learn":[0.0925080075],"iteration":852,"passed_time":26.37413,"remaining_time":4.545131431},
{"learn":[0.09242498173],"iteration":853,"passed_time":26.41050913,"remaining_time":4.515145589},
{"learn":[0.09230516939],"iteration":854,"passed_time":26.43665739,"remaining_time":4.483409734},
{"learn":[0.09220926201],"iteration":855,"passed_time":26.46053733,"remaining_time":4.451305346},
{"learn":[0.09207186979],"iteration":856,"passed_time":26.48770879,"remaining_time":4.419769378},
{"learn":[0.09187785317],"iteration":857,"passed_time":26.516177,"remaining_time":4.388458198},
{"learn":[0.09169706176],"iteration":858,"passed_time":26.53993146,"remaining_time":4.356379902},
{"learn":[0.09150123596],"iteration":859,"passed_time":26.56715128,"remaining_time":4.324885092},
{"learn":[0.09128465372],"iteration":860,"passed_time":26.59202099,"remaining_time":4.29302081},
{"learn":[0.09110371506],"iteration":861,"passed_time":26.61836991,"remaining_time":4.261409568},
{"learn":[0.09102147467],"iteration":862,"passed_time":26.64454464,"remaining_time":4.229782868},
{"learn":[0.09089212558],"iteration":863,"passed_time":26.66895784,"remaining_time":4.197891512},
{"learn":[0.09073307935],"iteration":864,"passed_time":26.69754697,"remaining_time":4.16666918},
{"learn":[0.09069791962],"iteration":865,"passed_time":26.72129396,"remaining_time":4.134703684},
{"learn":[0.09050986346],"iteration":866,"passed_time":26.74574869,"remaining_time":4.102865716},
{"learn":[0.09041893482],"iteration":867,"passed_time":26.77068514,"remaining_time":4.071118017},
{"learn":[0.09035058583],"iteration":868,"passed_time":26.79907177,"remaining_time":4.039906101},
{"learn":[0.09026440452],"iteration":869,"passed_time":26.8325366,"remaining_time":4.009459492},
{"learn":[0.09009936277],"iteration":870,"passed_time":26.8577164,"remaining_time":3.977778893},
{"learn":[0.08993851437],"iteration":871,"passed_time":26.88312635,"remaining_time":3.946146987},
{"learn":[0.08981425622],"iteration":872,"passed_time":26.91071741,"remaining_time":3.914846634},
{"learn":[0.08960187435],"iteration":873,"passed_time":26.93410669,"remaining_time":3.88294902},
{"learn":[0.08950750267],"iteration":874,"passed_time":26.95985079,"remaining_time":3.851407256},
{"learn":[0.08935964809],"iteration":875,"passed_time":26.98346323,"remaining_time":3.819576987},
{"learn":[0.08921732622],"iteration":876,"passed_time":27.0112966,"remaining_time":3.788357448},
{"learn":[0.08911999534],"iteration":877,"passed_time":27.03655272,"remaining_time":3.756787508},
{"learn":[0.08907501137],"iteration":878,"passed_time":27.06160138,"remaining_time":3.725203375},
{"learn":[0.08898204916],"iteration":879,"passed_time":27.08679929,"remaining_time":3.693654449},
{"learn":[0.08879398598],"iteration":880,"passed_time":27.11284519,"remaining_time":3.662234481},
{"learn":[0.08864674147],"iteration":881,"passed_time":27.13960639,"remaining_time":3.630922398},
{"learn":[0.08855902447],"iteration":882,"passed_time":27.16307282,"remaining_time":3.599184055},
{"learn":[0.08839796571],"iteration":883,"passed_time":27.1900814,"remaining_time":3.567929234},
{"learn":[0.08819549224],"iteration":884,"passed_time":27.21775358,"remaining_time":3.536770239},
{"learn":[0.08806951607],"iteration":885,"passed_time":27.24257734,"remaining_time":3.505252615},
{"learn":[0.08798770344],"iteration":886,"passed_time":27.27571218,"remaining_time":3.47480888},
{"learn":[0.08779260691],"iteration":887,"passed_time":27.30213389,"remaining_time":3.443512383},
{"learn":[0.08771775751],"iteration":888,"passed_time":27.32636094,"remaining_time":3.411952829},
{"learn":[0.08750897295],"iteration":889,"passed_time":27.3526686,"remaining_time":3.380666905},
{"learn":[0.08742633287],"iteration":890,"passed_time":27.38106415,"remaining_time":3.349647579},
{"learn":[0.0873474093],"iteration":891,"passed_time":27.40456351,"remaining_time":3.318041321},
{"learn":[0.08726413811],"iteration":892,"passed_time":27.43167385,"remaining_time":3.286885893},
{"learn":[0.08711407465],"iteration":893,"passed_time":27.4570827,"remaining_time":3.255537769},
{"learn":[0.08695987393],"iteration":894,"passed_time":27.48552435,"remaining_time":3.224558722},
{"learn":[0.08684655498],"iteration":895,"passed_time":27.51129357,"remaining_time":3.193275147},
{"learn":[0.08669126735],"iteration":896,"passed_time":27.54124244,"remaining_time":3.162483803},
{"learn":[0.08651176621],"iteration":897,"passed_time":27.56776031,"remaining_time":3.131304623},
{"learn":[0.08637327306],"iteration":898,"passed_time":27.59158695,"remaining_time":3.099833461},
{"learn":[0.08617874454],"iteration":899,"passed_time":27.62510062,"remaining_time":3.069455624},
{"learn":[0.08608488476],"iteration":900,"passed_time":27.65376053,"remaining_time":3.038537505},
{"learn":[0.08597216887],"iteration":901,"passed_time":27.69563801,"remaining_time":3.009060449},
{"learn":[0.08579268876],"iteration":902,"passed_time":27.71965175,"remaining_time":2.97763701},
{"learn":[0.08562998211],"iteration":903,"passed_time":27.74802038,"remaining_time":2.94669243},
{"learn":[0.08544297779],"iteration":904,"passed_time":27.77077654,"remaining_time":2.915164388},
{"learn":[0.0853014413],"iteration":905,"passed_time":27.79513047,"remaining_time":2.883821484},
{"learn":[0.08509904497],"iteration":906,"passed_time":27.81840373,"remaining_time":2.852383183},
{"learn":[0.08492577777],"iteration":907,"passed_time":27.84583401,"remaining_time":2.821384062},
{"learn":[0.08482210776],"iteration":908,"passed_time":27.8687642,"remaining_time":2.789942291},
{"learn":[0.08471204253],"iteration":909,"passed_time":27.89346014,"remaining_time":2.75869386},
{"learn":[0.0846053432],"iteration":910,"passed_time":27.91660275,"remaining_time":2.727308062},
{"learn":[0.08447705998],"iteration":911,"passed_time":27.94247536,"remaining_time":2.696203763},
{"learn":[0.08435605554],"iteration":912,"passed_time":27.96549803,"remaining_time":2.664839352},
{"learn":[0.08422349481],"iteration":913,"passed_time":27.98897416,"remaining_time":2.633535862},
{"learn":[0.08410578616],"iteration":914,"passed_time":28.0116116,"remaining_time":2.60217157},
{"learn":[0.08397785355],"iteration":915,"passed_time":28.03592049,"remaining_time":2.570979608},
{"learn":[0.08388501055],"iteration":916,"passed_time":28.06082473,"remaining_time":2.539856546},
{"learn":[0.08370053067],"iteration":917,"passed_time":28.08423244,"remaining_time":2.508613355},
{"learn":[0.0836438151],"iteration":918,"passed_time":28.11367781,"remaining_time":2.477919371},
{"learn":[0.08355921156],"iteration":919,"passed_time":28.13866358,"remaining_time":2.446840312},
{"learn":[0.08342430171],"iteration":920,"passed_time":28.16439753,"remaining_time":2.415838659},
{"learn":[0.08326608994],"iteration":921,"passed_time":28.19054518,"remaining_time":2.384883431},
{"learn":[0.08318719443],"iteration":922,"passed_time":28.21309697,"remaining_time":2.353638642},
{"learn":[0.08299821966],"iteration":923,"passed_time":28.23666371,"remaining_time":2.32249615},
{"learn":[0.0828434299],"iteration":924,"passed_time":28.26118458,"remaining_time":2.291447398},
{"learn":[0.0827339537],"iteration":925,"passed_time":28.28698102,"remaining_time":2.260514682},
{"learn":[0.0825653006],"iteration":926,"passed_time":28.31226338,"remaining_time":2.229552564},
{"learn":[0.08232522011],"iteration":927,"passed_time":28.34086531,"remaining_time":2.19886024},
{"learn":[0.08216285706],"iteration":928,"passed_time":28.38176305,"remaining_time":2.169112138},
{"learn":[0.08214135731],"iteration":929,"passed_time":28.40984909,"remaining_time":2.138375738},
{"learn":[0.08205421532],"iteration":930,"passed_time":28.43528186,"remaining_time":2.107448387},
{"learn":[0.08198839777],"iteration":931,"passed_time":28.45984999,"remaining_time":2.076469742},
{"learn":[0.08187373245],"iteration":932,"passed_time":28.48852634,"remaining_time":2.045799855},
{"learn":[0.08170787727],"iteration":933,"passed_time":28.5170429,"remaining_time":2.015122946},
{"learn":[0.08155101888],"iteration":934,"passed_time":28.54660138,"remaining_time":1.98452309},
{"learn":[0.08137488365],"iteration":935,"passed_time":28.57106334,"remaining_time":1.95357698},
{"learn":[0.08128589742],"iteration":936,"passed_time":28.59944819,"remaining_time":1.922908469},
{"learn":[0.08115617668],"iteration":937,"passed_time":28.62306458,"remaining_time":1.891929642},
{"learn":[0.08105557105],"iteration":938,"passed_time":28.64878857,"remaining_time":1.861103411},
{"learn":[0.08086047453],"iteration":939,"passed_time":28.67493519,"remaining_time":1.830315012},
{"learn":[0.0807270022],"iteration":940,"passed_time":28.70109921,"remaining_time":1.79953757},
{"learn":[0.08071501816],"iteration":941,"passed_time":28.72520684,"remaining_time":1.768643309},
{"learn":[0.0805496889],"iteration":942,"passed_time":28.74893199,"remaining_time":1.737740322},
{"learn":[0.08038007512],"iteration":943,"passed_time":28.77307331,"remaining_time":1.70687723},
{"learn":[0.08032945324],"iteration":944,"passed_time":28.80063634,"remaining_time":1.676227512},
{"learn":[0.08018368833],"iteration":945,"passed_time":28.8271995,"remaining_time":1.645527244},
{"learn":[0.07999943986],"iteration":946,"passed_time":28.8513755,"remaining_time":1.614702114},
{"learn":[0.07986802915],"iteration":947,"passed_time":28.87685372,"remaining_time":1.58396244},
{"learn":[0.07979644046],"iteration":948,"passed_time":28.90160921,"remaining_time":1.553195015},
{"learn":[0.07970260171],"iteration":949,"passed_time":28.9308792,"remaining_time":1.522677853},
{"learn":[0.07958597295],"iteration":950,"passed_time":28.95687308,"remaining_time":1.491994512},
{"learn":[0.07944780939],"iteration":951,"passed_time":28.98125217,"remaining_time":1.461239605},
{"learn":[0.07925152779],"iteration":952,"passed_time":29.00701644,"remaining_time":1.430566393},
{"learn":[0.07915133588],"iteration":953,"passed_time":29.03120397,"remaining_time":1.399827445},
{"learn":[0.07912837758],"iteration":954,"passed_time":29.05654956,"remaining_time":1.369156785},
{"learn":[0.0789649767],"iteration":955,"passed_time":29.08183184,"remaining_time":1.338494352},
{"learn":[0.07890061771],"iteration":956,"passed_time":29.11006167,"remaining_time":1.307975603},
{"learn":[0.07876808503],"iteration":957,"passed_time":29.13656992,"remaining_time":1.277386155},
{"learn":[0.07864625314],"iteration":958,"passed_time":29.16308867,"remaining_time":1.246805668},
{"learn":[0.07853503788],"iteration":959,"passed_time":29.18807757,"remaining_time":1.216169899},
{"learn":[0.07843246179],"iteration":960,"passed_time":29.21193347,"remaining_time":1.185499902},
{"learn":[0.07828535753],"iteration":961,"passed_time":29.23872342,"remaining_time":1.154959969},
{"learn":[0.07816955623],"iteration":962,"passed_time":29.26320795,"remaining_time":1.124339246},
{"learn":[0.07810755337],"iteration":963,"passed_time":29.28881238,"remaining_time":1.093773077},
{"learn":[0.07801346218],"iteration":964,"passed_time":29.31257999,"remaining_time":1.063150569},
{"learn":[0.07790671377],"iteration":965,"passed_time":29.34530195,"remaining_time":1.032857418},
{"learn":[0.0778073423],"iteration":966,"passed_time":29.37827156,"remaining_time":1.002567695},
{"learn":[0.07771545298],"iteration":967,"passed_time":29.41495966,"remaining_time":0.9723953608},
{"learn":[0.07758473649],"iteration":968,"passed_time":29.4418332,"remaining_time":0.9418955924},
{"learn":[0.07742503811],"iteration":969,"passed_time":29.46885411,"remaining_time":0.9114078591},
{"learn":[0.0773089493],"iteration":970,"passed_time":29.49668675,"remaining_time":0.8809515095},
{"learn":[0.07713601168],"iteration":971,"passed_time":29.52540493,"remaining_time":0.8505260678},
{"learn":[0.07703220844],"iteration":972,"passed_time":29.55397316,"remaining_time":0.8200999747},
{"learn":[0.07693473031],"iteration":973,"passed_time":29.57761873,"remaining_time":0.7895462906},
{"learn":[0.07675964692],"iteration":974,"passed_time":29.60528404,"remaining_time":0.7591098472},
{"learn":[0.07662869902],"iteration":975,"passed_time":29.63805693,"remaining_time":0.7288046785},
{"learn":[0.07652796717],"iteration":976,"passed_time":29.665237,"remaining_time":0.6983627953},
{"learn":[0.07641347717],"iteration":977,"passed_time":29.68947325,"remaining_time":0.6678613614},
{"learn":[0.07631622343],"iteration":978,"passed_time":29.71675881,"remaining_time":0.6374381359},
{"learn":[0.07617564061],"iteration":979,"passed_time":29.74094944,"remaining_time":0.6069581519},
{"learn":[0.07613557928],"iteration":980,"passed_time":29.76493471,"remaining_time":0.5764870127},
{"learn":[0.0759681323],"iteration":981,"passed_time":29.79493038,"remaining_time":0.5461392534},
{"learn":[0.07582675709],"iteration":982,"passed_time":29.81823931,"remaining_time":0.5156765699},
{"learn":[0.07571978429],"iteration":983,"passed_time":29.84522281,"remaining_time":0.4852881758},
{"learn":[0.07553612485],"iteration":984,"passed_time":29.86951221,"remaining_time":0.4548656682},
{"learn":[0.07542646632],"iteration":985,"passed_time":29.89480407,"remaining_time":0.4244698346},
{"learn":[0.07521977845],"iteration":986,"passed_time":29.91953136,"remaining_time":0.3940769075},
{"learn":[0.07512688637],"iteration":987,"passed_time":29.94711466,"remaining_time":0.3637301376},
{"learn":[0.07510737812],"iteration":988,"passed_time":29.97175525,"remaining_time":0.3333562262},
{"learn":[0.07496326811],"iteration":989,"passed_time":30.00021775,"remaining_time":0.3030325025},
{"learn":[0.07487270411],"iteration":990,"passed_time":30.03094937,"remaining_time":0.2727331426},
{"learn":[0.07467973934],"iteration":991,"passed_time":30.05746273,"remaining_time":0.242398893},
{"learn":[0.0745101536],"iteration":992,"passed_time":30.08339503,"remaining_time":0.2120682429},
{"learn":[0.07441403585],"iteration":993,"passed_time":30.10775655,"remaining_time":0.1817369611},
{"learn":[0.0742598772],"iteration":994,"passed_time":30.13702482,"remaining_time":0.1514423358},
{"learn":[0.07412497436],"iteration":995,"passed_time":30.16847586,"remaining_time":0.1211585376},
{"learn":[0.07400011315],"iteration":996,"passed_time":30.19297383,"remaining_time":0.09085147591},
{"learn":[0.07391491357],"iteration":997,"passed_time":30.22208402,"remaining_time":0.06056529864},
{"learn":[0.07379976441],"iteration":998,"passed_time":30.24683715,"remaining_time":0.03027711427},
{"learn":[0.07369625568],"iteration":999,"passed_time":30.27355826,"remaining_time":0}
]}